{
  "schemaVersion": 1,
  "slug": "pl.91d1e6bdee7e439da9c8f1d10a4519a0",
  "parentSlug": "premium-playlists",
  "title": "Sad, Bitter, and Angry",
  "subtitle": "Updated Playlist",
  "kind": "playlist",
  "coverImage": "https://is1-ssl.mzstatic.com/image/thumb/Features115/v4/c1/7d/af/c17daf89-a701-4ca3-07e9-cd08acadde09/U0MtTVMtV1ctU2FkX19CaXR0ZXJfYW5kX0FuZ3J5LUFEQU1fSUQ9OTc2NDU5MDQwLnBuZw.png/296x296SC.DN01.webp?l=en-US",
  "appleUrl": "https://music.apple.com/us/playlist/sad-bitter-and-angry/pl.91d1e6bdee7e439da9c8f1d10a4519a0",
  "appleId": "pl.91d1e6bdee7e439da9c8f1d10a4519a0",
  "market": "US",
  "trackCount": 100,
  "updatedAt": "2026-07-22T08:44:11.465Z",
  "stale": false,
  "tracks": [
    {
      "position": 1,
      "title": "R.I.P.",
      "artistNames": [
        "Motionless In White & Skylar Grey"
      ],
      "artists": [
        {
          "name": "Motionless In White & Skylar Grey",
          "appleUrl": null
        }
      ],
      "album": {
        "name": "Decades",
        "releaseDate": null,
        "coverImage": "https://is1-ssl.mzstatic.com/image/thumb/Music211/v4/ec/c5/45/ecc54584-3fd6-446b-66f5-5eae301a3ea6/075679578396.jpg/600x600bb.jpg",
        "appleUrl": "https://music.apple.com/us/album/r-i-p/1896071360"
      },
      "durationMs": 240110,
      "explicit": true,
      "appleUrl": "https://music.apple.com/us/album/r-i-p/1896071360?i=6765780291",
      "appleId": "6765780291"
    },
    {
      "position": 2,
      "title": "Love Me",
      "artistNames": [
        "The Pretty Reckless"
      ],
      "artists": [
        {
          "name": "The Pretty Reckless",
          "appleUrl": null
        }
      ],
      "album": {
        "name": "Dear God",
        "releaseDate": null,
        "coverImage": "https://is1-ssl.mzstatic.com/image/thumb/Music221/v4/7a/04/ed/7a04ed0c-b477-cf86-18a4-411db9c0c8b6/25CRGIM51366.rgb.jpg/600x600bb.jpg",
        "appleUrl": "https://music.apple.com/us/album/love-me/1878237662"
      },
      "durationMs": 263279,
      "explicit": false,
      "appleUrl": "https://music.apple.com/us/album/love-me/1878237662?i=1878237810",
      "appleId": "1878237810"
    },
    {
      "position": 3,
      "title": "Nothing Else Matters",
      "artistNames": [
        "Metallica"
      ],
      "artists": [
        {
          "name": "Metallica",
          "appleUrl": null
        }
      ],
      "album": {
        "name": "Metallica (Remastered)",
        "releaseDate": null,
        "coverImage": "https://is1-ssl.mzstatic.com/image/thumb/Music125/v4/9e/80/1b/9e801b06-67fa-0990-2d15-85480ad3cd46/850007452025.png/600x600bb.jpg",
        "appleUrl": "https://music.apple.com/us/album/nothing-else-matters/1572046434"
      },
      "durationMs": 388733,
      "explicit": false,
      "appleUrl": "https://music.apple.com/us/album/nothing-else-matters/1572046434?i=1572046444",
      "appleId": "1572046444"
    },
    {
      "position": 4,
      "title": "How the Gods Kill",
      "artistNames": [
        "Danzig"
      ],
      "artists": [
        {
          "name": "Danzig",
          "appleUrl": null
        }
      ],
      "album": {
        "name": "Danzig III: How the Gods Kill",
        "releaseDate": null,
        "coverImage": "https://is1-ssl.mzstatic.com/image/thumb/Music124/v4/35/72/98/35729818-2a05-4ae2-1058-f655acc4028d/00602557176735.rgb.jpg/600x600bb.jpg",
        "appleUrl": "https://music.apple.com/us/album/how-the-gods-kill/1440900777"
      },
      "durationMs": 358438,
      "explicit": false,
      "appleUrl": "https://music.apple.com/us/album/how-the-gods-kill/1440900777?i=1440901213",
      "appleId": "1440901213"
    },
    {
      "position": 5,
      "title": "The Rising Skyline",
      "artistNames": [
        "Failure & Hayley Williams"
      ],
      "artists": [
        {
          "name": "Failure & Hayley Williams",
          "appleUrl": null
        }
      ],
      "album": {
        "name": "Location Lost",
        "releaseDate": null,
        "coverImage": "https://is1-ssl.mzstatic.com/image/thumb/Music211/v4/f8/02/74/f802742c-f1b0-6de3-3d6a-841b1f519420/198704937330_Cover.jpg/600x600bb.jpg",
        "appleUrl": "https://music.apple.com/us/album/the-rising-skyline/1867015665"
      },
      "durationMs": 272789,
      "explicit": false,
      "appleUrl": "https://music.apple.com/us/album/the-rising-skyline/1867015665?i=1867015669",
      "appleId": "1867015669"
    },
    {
      "position": 6,
      "title": "Gethsemane",
      "artistNames": [
        "Sleep Token"
      ],
      "artists": [
        {
          "name": "Sleep Token",
          "appleUrl": null
        }
      ],
      "album": {
        "name": "Even In Arcadia",
        "releaseDate": null,
        "coverImage": "https://is1-ssl.mzstatic.com/image/thumb/Music211/v4/45/76/46/457646e0-7bba-770b-f18c-12f7b479dca6/196872847215.jpg/600x600bb.jpg",
        "appleUrl": "https://music.apple.com/us/album/gethsemane/1800532611"
      },
      "durationMs": 383400,
      "explicit": false,
      "appleUrl": "https://music.apple.com/us/album/gethsemane/1800532611?i=1800534038",
      "appleId": "1800534038"
    },
    {
      "position": 7,
      "title": "Wasted Time",
      "artistNames": [
        "Skid Row"
      ],
      "artists": [
        {
          "name": "Skid Row",
          "appleUrl": null
        }
      ],
      "album": {
        "name": "Slave to the Grind",
        "releaseDate": null,
        "coverImage": "https://is1-ssl.mzstatic.com/image/thumb/Music116/v4/7f/3e/c3/7f3ec3ea-0ce9-0512-5842-78a85db07d0f/0603497968008.jpg/600x600bb.jpg",
        "appleUrl": "https://music.apple.com/us/album/wasted-time/1727313193"
      },
      "durationMs": 348760,
      "explicit": false,
      "appleUrl": "https://music.apple.com/us/album/wasted-time/1727313193?i=1727314036",
      "appleId": "1727314036"
    },
    {
      "position": 8,
      "title": "DOOM LOOP",
      "artistNames": [
        "PRESIDENT"
      ],
      "artists": [
        {
          "name": "PRESIDENT",
          "appleUrl": null
        }
      ],
      "album": {
        "name": "Blood Of Your Empire",
        "releaseDate": null,
        "coverImage": "https://is1-ssl.mzstatic.com/image/thumb/Music221/v4/50/8d/60/508d606b-88a2-7def-5dd3-e5a37f38326f/075679576392.jpg/600x600bb.jpg",
        "appleUrl": "https://music.apple.com/us/album/doom-loop/6769905842"
      },
      "durationMs": 240973,
      "explicit": false,
      "appleUrl": "https://music.apple.com/us/album/doom-loop/6769905842?i=6769906140",
      "appleId": "6769906140"
    },
    {
      "position": 9,
      "title": "All For You",
      "artistNames": [
        "Atreyu"
      ],
      "artists": [
        {
          "name": "Atreyu",
          "appleUrl": null
        }
      ],
      "album": {
        "name": "The End is Not the End",
        "releaseDate": null,
        "coverImage": "https://is1-ssl.mzstatic.com/image/thumb/Music221/v4/31/a5/1c/31a51cd9-1e67-b30f-a6f6-a161f9796109/5401148010749_cover.jpg/600x600bb.jpg",
        "appleUrl": "https://music.apple.com/us/album/all-for-you/1873285466"
      },
      "durationMs": 234235,
      "explicit": true,
      "appleUrl": "https://music.apple.com/us/album/all-for-you/1873285466?i=1873285937",
      "appleId": "1873285937"
    },
    {
      "position": 10,
      "title": "Love Bites",
      "artistNames": [
        "Def Leppard"
      ],
      "artists": [
        {
          "name": "Def Leppard",
          "appleUrl": null
        }
      ],
      "album": {
        "name": "Hysteria",
        "releaseDate": null,
        "coverImage": "https://is1-ssl.mzstatic.com/image/thumb/Music115/v4/0f/76/fa/0f76fa8d-8341-c0af-84d8-543b9193c728/17UM1IM41552.rgb.jpg/600x600bb.jpg",
        "appleUrl": "https://music.apple.com/us/album/love-bites/1440903625"
      },
      "durationMs": 346985,
      "explicit": false,
      "appleUrl": "https://music.apple.com/us/album/love-bites/1440903625?i=1440904256",
      "appleId": "1440904256"
    },
    {
      "position": 11,
      "title": "Bloodlust",
      "artistNames": [
        "Dayseeker"
      ],
      "artists": [
        {
          "name": "Dayseeker",
          "appleUrl": null
        }
      ],
      "album": {
        "name": "Creature In The Black Night",
        "releaseDate": null,
        "coverImage": "https://is1-ssl.mzstatic.com/image/thumb/Music221/v4/74/3e/71/743e710f-bae5-0942-84a0-ce41a57c8b43/5401148008449_cover.jpg/600x600bb.jpg",
        "appleUrl": "https://music.apple.com/us/album/bloodlust/1823938916"
      },
      "durationMs": 209987,
      "explicit": false,
      "appleUrl": "https://music.apple.com/us/album/bloodlust/1823938916?i=1823939338",
      "appleId": "1823939338"
    },
    {
      "position": 12,
      "title": "So Cold",
      "artistNames": [
        "Breaking Benjamin"
      ],
      "artists": [
        {
          "name": "Breaking Benjamin",
          "appleUrl": null
        }
      ],
      "album": {
        "name": "We Are Not Alone",
        "releaseDate": null,
        "coverImage": "https://is1-ssl.mzstatic.com/image/thumb/Music115/v4/e7/0c/e7/e70ce7b3-806d-1ae1-6b4b-b387fdd76ba1/00050087153472.rgb.jpg/600x600bb.jpg",
        "appleUrl": "https://music.apple.com/us/album/so-cold/1440809386"
      },
      "durationMs": 273440,
      "explicit": false,
      "appleUrl": "https://music.apple.com/us/album/so-cold/1440809386?i=1440809397",
      "appleId": "1440809397"
    },
    {
      "position": 13,
      "title": "i think about you all the time",
      "artistNames": [
        "Deftones"
      ],
      "artists": [
        {
          "name": "Deftones",
          "appleUrl": null
        }
      ],
      "album": {
        "name": "private music",
        "releaseDate": null,
        "coverImage": "https://is1-ssl.mzstatic.com/image/thumb/Music211/v4/e3/04/cf/e304cf55-06c7-8b6c-34d3-95b2706c79a8/093624832232.jpg/600x600bb.jpg",
        "appleUrl": "https://music.apple.com/us/album/i-think-about-you-all-the-time/1825435148"
      },
      "durationMs": 248957,
      "explicit": false,
      "appleUrl": "https://music.apple.com/us/album/i-think-about-you-all-the-time/1825435148?i=1825435158",
      "appleId": "1825435158"
    },
    {
      "position": 14,
      "title": "Fangs",
      "artistNames": [
        "Loathe"
      ],
      "artists": [
        {
          "name": "Loathe",
          "appleUrl": null
        }
      ],
      "album": {
        "name": "A Stranger To You",
        "releaseDate": null,
        "coverImage": "https://is1-ssl.mzstatic.com/image/thumb/Music211/v4/6a/72/76/6a72767b-3119-d895-e8dd-649b45ab25ba/cover.jpg/600x600bb.jpg",
        "appleUrl": "https://music.apple.com/us/album/fangs/1895184628"
      },
      "durationMs": 249293,
      "explicit": false,
      "appleUrl": "https://music.apple.com/us/album/fangs/1895184628?i=6763148062",
      "appleId": "6763148062"
    },
    {
      "position": 15,
      "title": "Drown (New)",
      "artistNames": [
        "Bring Me The Horizon"
      ],
      "artists": [
        {
          "name": "Bring Me The Horizon",
          "appleUrl": null
        }
      ],
      "album": {
        "name": "That's the Spirit",
        "releaseDate": null,
        "coverImage": "https://is1-ssl.mzstatic.com/image/thumb/Music116/v4/bb/dc/1d/bbdc1dda-00d3-f989-0599-543da601acaf/886445386097.jpg/600x600bb.jpg",
        "appleUrl": "https://music.apple.com/us/album/drown-new/1021582747"
      },
      "durationMs": 222093,
      "explicit": false,
      "appleUrl": "https://music.apple.com/us/album/drown-new/1021582747?i=1021582767",
      "appleId": "1021582767"
    },
    {
      "position": 16,
      "title": "Teacher",
      "artistNames": [
        "Warning"
      ],
      "artists": [
        {
          "name": "Warning",
          "appleUrl": null
        }
      ],
      "album": {
        "name": "Rituals of Shame",
        "releaseDate": null,
        "coverImage": "https://is1-ssl.mzstatic.com/image/thumb/Music221/v4/cb/d8/b4/cbd8b4f0-e800-23bb-a596-399501e24a2c/781676556717.jpg/600x600bb.jpg",
        "appleUrl": "https://music.apple.com/us/album/teacher/1884088755"
      },
      "durationMs": 515051,
      "explicit": false,
      "appleUrl": "https://music.apple.com/us/album/teacher/1884088755?i=1884089399",
      "appleId": "1884089399"
    },
    {
      "position": 17,
      "title": "November Rain",
      "artistNames": [
        "Guns N' Roses"
      ],
      "artists": [
        {
          "name": "Guns N' Roses",
          "appleUrl": null
        }
      ],
      "album": {
        "name": "Use Your Illusion I",
        "releaseDate": null,
        "coverImage": "https://is1-ssl.mzstatic.com/image/thumb/Music112/v4/6a/e2/1f/6ae21fa9-c897-3be1-2967-50eefae22b93/06UMGIM05041.rgb.jpg/600x600bb.jpg",
        "appleUrl": "https://music.apple.com/us/album/november-rain/1440896026"
      },
      "durationMs": 536067,
      "explicit": false,
      "appleUrl": "https://music.apple.com/us/album/november-rain/1440896026?i=1440896193",
      "appleId": "1440896193"
    },
    {
      "position": 18,
      "title": "Sleeping with the Enemy",
      "artistNames": [
        "In This Moment"
      ],
      "artists": [
        {
          "name": "In This Moment",
          "appleUrl": null
        }
      ],
      "album": {
        "name": "Sleeping with the Enemy - Single",
        "releaseDate": null,
        "coverImage": "https://is1-ssl.mzstatic.com/image/thumb/Music211/v4/a5/fd/0a/a5fd0a54-7b7f-0398-ef98-20677c78d46a/810202538306.png/600x600bb.jpg",
        "appleUrl": "https://music.apple.com/us/album/sleeping-with-the-enemy/6769517601"
      },
      "durationMs": 246375,
      "explicit": false,
      "appleUrl": "https://music.apple.com/us/album/sleeping-with-the-enemy/6769517601?i=6769517602",
      "appleId": "6769517602"
    },
    {
      "position": 19,
      "title": "Hurt",
      "artistNames": [
        "Nine Inch Nails"
      ],
      "artists": [
        {
          "name": "Nine Inch Nails",
          "appleUrl": null
        }
      ],
      "album": {
        "name": "The Downward Spiral",
        "releaseDate": null,
        "coverImage": "https://is1-ssl.mzstatic.com/image/thumb/Music115/v4/55/e0/85/55e0851e-11df-3b6a-7c54-4eef0efc2bed/15UMGIM67680.rgb.jpg/600x600bb.jpg",
        "appleUrl": "https://music.apple.com/us/album/hurt/1440837096"
      },
      "durationMs": 373145,
      "explicit": false,
      "appleUrl": "https://music.apple.com/us/album/hurt/1440837096?i=1440838114",
      "appleId": "1440838114"
    },
    {
      "position": 20,
      "title": "Give Up",
      "artistNames": [
        "Overgrown"
      ],
      "artists": [
        {
          "name": "Overgrown",
          "appleUrl": null
        }
      ],
      "album": {
        "name": "Give Up - Single",
        "releaseDate": null,
        "coverImage": "https://is1-ssl.mzstatic.com/image/thumb/Music221/v4/5a/86/8f/5a868f8d-0a14-fd21-0c51-9b42c0988f32/810129963311.jpg/600x600bb.jpg",
        "appleUrl": "https://music.apple.com/us/album/give-up/1874689309"
      },
      "durationMs": 240000,
      "explicit": false,
      "appleUrl": "https://music.apple.com/us/album/give-up/1874689309?i=1874689317",
      "appleId": "1874689317"
    },
    {
      "position": 21,
      "title": "Far Behind",
      "artistNames": [
        "Candlebox"
      ],
      "artists": [
        {
          "name": "Candlebox",
          "appleUrl": null
        }
      ],
      "album": {
        "name": "Candlebox",
        "releaseDate": null,
        "coverImage": "https://is1-ssl.mzstatic.com/image/thumb/Music125/v4/1f/21/9d/1f219d66-2298-0bf9-97f2-b26af580793e/mzm.nssvbgfk.jpg/600x600bb.jpg",
        "appleUrl": "https://music.apple.com/us/album/far-behind/300983126"
      },
      "durationMs": 299733,
      "explicit": false,
      "appleUrl": "https://music.apple.com/us/album/far-behind/300983126?i=300983131",
      "appleId": "300983131"
    },
    {
      "position": 22,
      "title": "Aggressive Evolution",
      "artistNames": [
        "Loathe"
      ],
      "artists": [
        {
          "name": "Loathe",
          "appleUrl": null
        }
      ],
      "album": {
        "name": "I Let It in and It Took Everything",
        "releaseDate": null,
        "coverImage": "https://is1-ssl.mzstatic.com/image/thumb/Music123/v4/96/00/0d/96000d08-9403-fcfa-a865-178160a13313/cover.jpg/600x600bb.jpg",
        "appleUrl": "https://music.apple.com/us/album/aggressive-evolution/1487438250"
      },
      "durationMs": 207267,
      "explicit": false,
      "appleUrl": "https://music.apple.com/us/album/aggressive-evolution/1487438250?i=1487438633",
      "appleId": "1487438633"
    },
    {
      "position": 23,
      "title": "God Owes Me Money",
      "artistNames": [
        "Militarie Gun"
      ],
      "artists": [
        {
          "name": "Militarie Gun",
          "appleUrl": null
        }
      ],
      "album": {
        "name": "God Save The Gun",
        "releaseDate": null,
        "coverImage": "https://is1-ssl.mzstatic.com/image/thumb/Music211/v4/27/1f/58/271f58a5-642d-7505-6a8c-96ce06d79d37/25CRGIM50276.rgb.jpg/600x600bb.jpg",
        "appleUrl": "https://music.apple.com/us/album/god-owes-me-money/1821959132"
      },
      "durationMs": 201594,
      "explicit": false,
      "appleUrl": "https://music.apple.com/us/album/god-owes-me-money/1821959132?i=1821959138",
      "appleId": "1821959138"
    },
    {
      "position": 24,
      "title": "Lachryma",
      "artistNames": [
        "Ghost"
      ],
      "artists": [
        {
          "name": "Ghost",
          "appleUrl": null
        }
      ],
      "album": {
        "name": "Skeletá",
        "releaseDate": null,
        "coverImage": "https://is1-ssl.mzstatic.com/image/thumb/Music211/v4/79/43/d8/7943d8ce-0a53-cca2-bcfb-8377c16bacdc/24CRGIM46415.rgb.jpg/600x600bb.jpg",
        "appleUrl": "https://music.apple.com/us/album/lachryma/1796483834"
      },
      "durationMs": 276403,
      "explicit": false,
      "appleUrl": "https://music.apple.com/us/album/lachryma/1796483834?i=1796483915",
      "appleId": "1796483915"
    },
    {
      "position": 25,
      "title": "Babe I'm Gonna Leave You",
      "artistNames": [
        "Led Zeppelin"
      ],
      "artists": [
        {
          "name": "Led Zeppelin",
          "appleUrl": null
        }
      ],
      "album": {
        "name": "Led Zeppelin (Remastered)",
        "releaseDate": null,
        "coverImage": "https://is1-ssl.mzstatic.com/image/thumb/Music114/v4/4c/7b/80/4c7b80b4-ed35-4e06-ec80-2f7aaaabb5c5/dj.pjjmtwdc.jpg/600x600bb.jpg",
        "appleUrl": "https://music.apple.com/us/album/babe-im-gonna-leave-you/580708520"
      },
      "durationMs": 402760,
      "explicit": false,
      "appleUrl": "https://music.apple.com/us/album/babe-im-gonna-leave-you/580708520?i=580708941",
      "appleId": "580708941"
    },
    {
      "position": 26,
      "title": "Goodbye to Romance",
      "artistNames": [
        "Ozzy Osbourne"
      ],
      "artists": [
        {
          "name": "Ozzy Osbourne",
          "appleUrl": null
        }
      ],
      "album": {
        "name": "Blizzard of Ozz (40th Anniversary Expanded Edition)",
        "releaseDate": null,
        "coverImage": "https://is1-ssl.mzstatic.com/image/thumb/Music114/v4/92/06/bd/9206bdb3-453a-db69-44f4-c4b5bfe33510/886448748045.jpg/600x600bb.jpg",
        "appleUrl": "https://music.apple.com/us/album/goodbye-to-romance/1531535089"
      },
      "durationMs": 335872,
      "explicit": false,
      "appleUrl": "https://music.apple.com/us/album/goodbye-to-romance/1531535089?i=1531535288",
      "appleId": "1531535288"
    },
    {
      "position": 27,
      "title": "Crying Fire",
      "artistNames": [
        "Avatar"
      ],
      "artists": [
        {
          "name": "Avatar",
          "appleUrl": null
        }
      ],
      "album": {
        "name": "Crying Fire - Single",
        "releaseDate": null,
        "coverImage": "https://is1-ssl.mzstatic.com/image/thumb/Music211/v4/de/23/40/de234013-a2e4-5679-46a4-a8913ee7589d/820233257718.jpg/600x600bb.jpg",
        "appleUrl": "https://music.apple.com/us/album/crying-fire/1896273209"
      },
      "durationMs": 248384,
      "explicit": false,
      "appleUrl": "https://music.apple.com/us/album/crying-fire/1896273209?i=6766303435",
      "appleId": "6766303435"
    },
    {
      "position": 28,
      "title": "The Red",
      "artistNames": [
        "Chevelle"
      ],
      "artists": [
        {
          "name": "Chevelle",
          "appleUrl": null
        }
      ],
      "album": {
        "name": "Wonder What's Next (Expanded Edition)",
        "releaseDate": null,
        "coverImage": "https://is1-ssl.mzstatic.com/image/thumb/Music124/v4/5e/a4/00/5ea400c9-fba3-f453-c6b0-8572752263f8/mzi.jubchflz.jpg/600x600bb.jpg",
        "appleUrl": "https://music.apple.com/us/album/the-red/270139029"
      },
      "durationMs": 238400,
      "explicit": false,
      "appleUrl": "https://music.apple.com/us/album/the-red/270139029?i=270139035",
      "appleId": "270139035"
    },
    {
      "position": 29,
      "title": "End of You",
      "artistNames": [
        "Poppy, Amy Lee & Courtney LaPlante"
      ],
      "artists": [
        {
          "name": "Poppy, Amy Lee & Courtney LaPlante",
          "appleUrl": null
        }
      ],
      "album": {
        "name": "End of You - Single",
        "releaseDate": null,
        "coverImage": "https://is1-ssl.mzstatic.com/image/thumb/Music211/v4/31/b4/a6/31b4a6c7-903e-639c-fbac-c9efe7e78c40/198704703461_Cover.jpg/600x600bb.jpg",
        "appleUrl": "https://music.apple.com/us/album/end-of-you/1837050617"
      },
      "durationMs": 192800,
      "explicit": false,
      "appleUrl": "https://music.apple.com/us/album/end-of-you/1837050617?i=1837050620",
      "appleId": "1837050620"
    },
    {
      "position": 30,
      "title": "The Crow & the Butterfly",
      "artistNames": [
        "Shinedown"
      ],
      "artists": [
        {
          "name": "Shinedown",
          "appleUrl": null
        }
      ],
      "album": {
        "name": "The Sound of Madness (Bonus Track Version)",
        "releaseDate": null,
        "coverImage": "https://is1-ssl.mzstatic.com/image/thumb/Features124/v4/2e/8e/08/2e8e0859-c522-a825-93fa-2db9c7524f38/dj.lcoxyovc.jpg/600x600bb.jpg",
        "appleUrl": "https://music.apple.com/us/album/the-crow-the-butterfly/279812117"
      },
      "durationMs": 253600,
      "explicit": false,
      "appleUrl": "https://music.apple.com/us/album/the-crow-the-butterfly/279812117?i=279812241",
      "appleId": "279812241"
    },
    {
      "position": 31,
      "title": "The Emptiness Machine",
      "artistNames": [
        "LINKIN PARK"
      ],
      "artists": [
        {
          "name": "LINKIN PARK",
          "appleUrl": null
        }
      ],
      "album": {
        "name": "From Zero",
        "releaseDate": null,
        "coverImage": "https://is1-ssl.mzstatic.com/image/thumb/Music211/v4/69/21/cf/6921cff3-7074-118a-ece2-4012450e6c75/093624839811.jpg/600x600bb.jpg",
        "appleUrl": "https://music.apple.com/us/album/the-emptiness-machine/1766137049"
      },
      "durationMs": 190428,
      "explicit": true,
      "appleUrl": "https://music.apple.com/us/album/the-emptiness-machine/1766137049?i=1766137051",
      "appleId": "1766137051"
    },
    {
      "position": 32,
      "title": "Aerials",
      "artistNames": [
        "System Of A Down"
      ],
      "artists": [
        {
          "name": "System Of A Down",
          "appleUrl": null
        }
      ],
      "album": {
        "name": "Toxicity",
        "releaseDate": null,
        "coverImage": "https://is1-ssl.mzstatic.com/image/thumb/Music125/v4/82/51/52/825152b4-9423-b23b-c036-cc67ead732d4/888888046775.jpg/600x600bb.jpg",
        "appleUrl": "https://music.apple.com/us/album/aerials/273714443"
      },
      "durationMs": 235053,
      "explicit": false,
      "appleUrl": "https://music.apple.com/us/album/aerials/273714443?i=273714765",
      "appleId": "273714765"
    },
    {
      "position": 33,
      "title": "Close My Eyes Forever",
      "artistNames": [
        "Lita Ford & Ozzy Osbourne"
      ],
      "artists": [
        {
          "name": "Lita Ford & Ozzy Osbourne",
          "appleUrl": null
        }
      ],
      "album": {
        "name": "Lita",
        "releaseDate": null,
        "coverImage": "https://is1-ssl.mzstatic.com/image/thumb/Music125/v4/10/a4/e6/10a4e6cb-9f42-354c-48dd-a66debf502a3/mzi.jfutyayf.jpg/600x600bb.jpg",
        "appleUrl": "https://music.apple.com/us/album/close-my-eyes-forever/298271951"
      },
      "durationMs": 283133,
      "explicit": false,
      "appleUrl": "https://music.apple.com/us/album/close-my-eyes-forever/298271951?i=298272119",
      "appleId": "298272119"
    },
    {
      "position": 34,
      "title": "Always",
      "artistNames": [
        "Saliva"
      ],
      "artists": [
        {
          "name": "Saliva",
          "appleUrl": null
        }
      ],
      "album": {
        "name": "Back Into Your System",
        "releaseDate": null,
        "coverImage": "https://is1-ssl.mzstatic.com/image/thumb/Music122/v4/f8/e0/01/f8e001bd-c4e1-5fce-7db1-af45568607b1/06UMGIM26381.rgb.jpg/600x600bb.jpg",
        "appleUrl": "https://music.apple.com/us/album/always/1422924587"
      },
      "durationMs": 231200,
      "explicit": false,
      "appleUrl": "https://music.apple.com/us/album/always/1422924587?i=1422924591",
      "appleId": "1422924591"
    },
    {
      "position": 35,
      "title": "Destroy Me",
      "artistNames": [
        "PRESIDENT"
      ],
      "artists": [
        {
          "name": "PRESIDENT",
          "appleUrl": null
        }
      ],
      "album": {
        "name": "King Of Terrors - EP",
        "releaseDate": null,
        "coverImage": "https://is1-ssl.mzstatic.com/image/thumb/Music211/v4/23/2e/57/232e574d-0f97-e687-797c-d8efa4f9fb62/5034644803487.jpg/600x600bb.jpg",
        "appleUrl": "https://music.apple.com/us/album/destroy-me/1823699240"
      },
      "durationMs": 162827,
      "explicit": true,
      "appleUrl": "https://music.apple.com/us/album/destroy-me/1823699240?i=1823699249",
      "appleId": "1823699249"
    },
    {
      "position": 36,
      "title": "Just Pretend",
      "artistNames": [
        "Bad Omens"
      ],
      "artists": [
        {
          "name": "Bad Omens",
          "appleUrl": null
        }
      ],
      "album": {
        "name": "THE DEATH OF PEACE OF MIND",
        "releaseDate": null,
        "coverImage": "https://is1-ssl.mzstatic.com/image/thumb/Music221/v4/f0/ce/0d/f0ce0d9c-934d-770d-e62f-74564fc410e1/00810016765424_Cover.jpg/600x600bb.jpg",
        "appleUrl": "https://music.apple.com/us/album/just-pretend/1817382334"
      },
      "durationMs": 204677,
      "explicit": false,
      "appleUrl": "https://music.apple.com/us/album/just-pretend/1817382334?i=1817382450",
      "appleId": "1817382450"
    },
    {
      "position": 37,
      "title": "About You",
      "artistNames": [
        "The Pretty Reckless"
      ],
      "artists": [
        {
          "name": "The Pretty Reckless",
          "appleUrl": null
        }
      ],
      "album": {
        "name": "Dear God",
        "releaseDate": null,
        "coverImage": "https://is1-ssl.mzstatic.com/image/thumb/Music221/v4/7a/04/ed/7a04ed0c-b477-cf86-18a4-411db9c0c8b6/25CRGIM51366.rgb.jpg/600x600bb.jpg",
        "appleUrl": "https://music.apple.com/us/album/about-you/1878237662"
      },
      "durationMs": 276096,
      "explicit": true,
      "appleUrl": "https://music.apple.com/us/album/about-you/1878237662?i=1878237815",
      "appleId": "1878237815"
    },
    {
      "position": 38,
      "title": "Sick of You",
      "artistNames": [
        "GWAR"
      ],
      "artists": [
        {
          "name": "GWAR",
          "appleUrl": null
        }
      ],
      "album": {
        "name": "Scumdogs of the Universe",
        "releaseDate": null,
        "coverImage": "https://is1-ssl.mzstatic.com/image/thumb/Music116/v4/e8/f6/e0/e8f6e0dd-7f17-ac44-f334-c622b95dd069/3183.jpg/600x600bb.jpg",
        "appleUrl": "https://music.apple.com/us/album/sick-of-you/1526590538"
      },
      "durationMs": 188830,
      "explicit": true,
      "appleUrl": "https://music.apple.com/us/album/sick-of-you/1526590538?i=1526590542",
      "appleId": "1526590542"
    },
    {
      "position": 39,
      "title": "tower of memories",
      "artistNames": [
        "ivri"
      ],
      "artists": [
        {
          "name": "ivri",
          "appleUrl": null
        }
      ],
      "album": {
        "name": "the theory of you",
        "releaseDate": null,
        "coverImage": "https://is1-ssl.mzstatic.com/image/thumb/Music221/v4/8d/3d/67/8d3d678a-dd56-78f4-3103-9db62f08abac/131.jpg/600x600bb.jpg",
        "appleUrl": "https://music.apple.com/us/album/tower-of-memories/1851073167"
      },
      "durationMs": 208510,
      "explicit": false,
      "appleUrl": "https://music.apple.com/us/album/tower-of-memories/1851073167?i=1851073171",
      "appleId": "1851073171"
    },
    {
      "position": 40,
      "title": "Call Me When You're Sober",
      "artistNames": [
        "Evanescence"
      ],
      "artists": [
        {
          "name": "Evanescence",
          "appleUrl": null
        }
      ],
      "album": {
        "name": "The Open Door",
        "releaseDate": null,
        "coverImage": "https://is1-ssl.mzstatic.com/image/thumb/Music124/v4/72/62/7e/72627ec6-772c-7229-6cc4-6ded693506fd/00601501412004.rgb.jpg/600x600bb.jpg",
        "appleUrl": "https://music.apple.com/us/album/call-me-when-youre-sober/1440634103"
      },
      "durationMs": 214707,
      "explicit": false,
      "appleUrl": "https://music.apple.com/us/album/call-me-when-youre-sober/1440634103?i=1440634107",
      "appleId": "1440634107"
    },
    {
      "position": 41,
      "title": "Wish You Were Here",
      "artistNames": [
        "Pink Floyd"
      ],
      "artists": [
        {
          "name": "Pink Floyd",
          "appleUrl": null
        }
      ],
      "album": {
        "name": "Wish You Were Here",
        "releaseDate": null,
        "coverImage": "https://is1-ssl.mzstatic.com/image/thumb/Music211/v4/aa/e0/ab/aae0ab6a-d906-a189-81bf-70b56aa43f7a/886445635843.jpg/600x600bb.jpg",
        "appleUrl": "https://music.apple.com/us/album/wish-you-were-here/1065973975"
      },
      "durationMs": 338467,
      "explicit": false,
      "appleUrl": "https://music.apple.com/us/album/wish-you-were-here/1065973975?i=1065973980",
      "appleId": "1065973980"
    },
    {
      "position": 42,
      "title": "I Hate Everything About You",
      "artistNames": [
        "Three Days Grace"
      ],
      "artists": [
        {
          "name": "Three Days Grace",
          "appleUrl": null
        }
      ],
      "album": {
        "name": "Three Days Grace",
        "releaseDate": null,
        "coverImage": "https://is1-ssl.mzstatic.com/image/thumb/Music211/v4/bb/b9/93/bbb9937d-8afd-69e2-c8f7-d9a1f20c0497/828765347921.jpg/600x600bb.jpg",
        "appleUrl": "https://music.apple.com/us/album/i-hate-everything-about-you/298376467"
      },
      "durationMs": 231411,
      "explicit": false,
      "appleUrl": "https://music.apple.com/us/album/i-hate-everything-about-you/298376467?i=298376639",
      "appleId": "298376639"
    },
    {
      "position": 43,
      "title": "We Might as Well Be Strangers (ft. Wednesday)",
      "artistNames": [
        "Weezer"
      ],
      "artists": [
        {
          "name": "Weezer",
          "appleUrl": null
        }
      ],
      "album": {
        "name": "Weezer",
        "releaseDate": null,
        "coverImage": "https://is1-ssl.mzstatic.com/image/thumb/Music211/v4/7b/4f/c6/7b4fc6dc-bb2a-4b73-0c58-fb1bd3e21102/093624819394.jpg/600x600bb.jpg",
        "appleUrl": "https://music.apple.com/us/album/we-might-as-well-be-strangers-ft-wednesday/6772364953"
      },
      "durationMs": 214347,
      "explicit": false,
      "appleUrl": "https://music.apple.com/us/album/we-might-as-well-be-strangers-ft-wednesday/6772364953?i=6772365051",
      "appleId": "6772365051"
    },
    {
      "position": 44,
      "title": "Deathblow",
      "artistNames": [
        "Deftones"
      ],
      "artists": [
        {
          "name": "Deftones",
          "appleUrl": null
        }
      ],
      "album": {
        "name": "Deftones",
        "releaseDate": null,
        "coverImage": "https://is1-ssl.mzstatic.com/image/thumb/Music125/v4/22/c9/01/22c9019c-96d8-d32f-26a9-bf98c9541df2/093624919780.jpg/600x600bb.jpg",
        "appleUrl": "https://music.apple.com/us/album/deathblow/1099847180"
      },
      "durationMs": 328240,
      "explicit": false,
      "appleUrl": "https://music.apple.com/us/album/deathblow/1099847180?i=1099847186",
      "appleId": "1099847186"
    },
    {
      "position": 45,
      "title": "Hate Me",
      "artistNames": [
        "Blue October"
      ],
      "artists": [
        {
          "name": "Blue October",
          "appleUrl": null
        }
      ],
      "album": {
        "name": "Foiled",
        "releaseDate": null,
        "coverImage": "https://is1-ssl.mzstatic.com/image/thumb/Music221/v4/1d/6d/bf/1d6dbfab-954a-166c-8354-231442b9c0f2/06UMGIM26036.rgb.jpg/600x600bb.jpg",
        "appleUrl": "https://music.apple.com/us/album/hate-me/1440778800"
      },
      "durationMs": 380200,
      "explicit": true,
      "appleUrl": "https://music.apple.com/us/album/hate-me/1440778800?i=1440779445",
      "appleId": "1440779445"
    },
    {
      "position": 46,
      "title": "Changes (feat. Adam Wakeman & II) [Live From Villa Park / Back To The Beginning]",
      "artistNames": [
        "YUNGBLUD, Nuno Bettencourt & Frank Bello"
      ],
      "artists": [
        {
          "name": "YUNGBLUD, Nuno Bettencourt & Frank Bello",
          "appleUrl": null
        }
      ],
      "album": {
        "name": "Changes (Live From Villa Park / Back To The Beginning) [feat. Adam Wakeman & II] - Single",
        "releaseDate": null,
        "coverImage": "https://is1-ssl.mzstatic.com/image/thumb/Music211/v4/49/cf/74/49cf74e4-2de2-65cf-064c-23c33fd3030f/25UMGIM94952.rgb.jpg/600x600bb.jpg",
        "appleUrl": "https://music.apple.com/us/album/changes-feat-adam-wakeman-ii-live-from-villa-park-back/1826660429"
      },
      "durationMs": 340359,
      "explicit": true,
      "appleUrl": "https://music.apple.com/us/album/changes-feat-adam-wakeman-ii-live-from-villa-park-back/1826660429?i=1826660430",
      "appleId": "1826660430"
    },
    {
      "position": 47,
      "title": "FEEL NOTHING",
      "artistNames": [
        "The Plot In You"
      ],
      "artists": [
        {
          "name": "The Plot In You",
          "appleUrl": null
        }
      ],
      "album": {
        "name": "DISPOSE",
        "releaseDate": null,
        "coverImage": "https://is1-ssl.mzstatic.com/image/thumb/Music115/v4/69/66/8d/69668dd7-d312-51f9-d752-e19961503b4f/00888072042698.rgb.jpg/600x600bb.jpg",
        "appleUrl": "https://music.apple.com/us/album/feel-nothing/1440944986"
      },
      "durationMs": 216827,
      "explicit": true,
      "appleUrl": "https://music.apple.com/us/album/feel-nothing/1440944986?i=1440944997",
      "appleId": "1440944997"
    },
    {
      "position": 48,
      "title": "Unravel",
      "artistNames": [
        "Poppy"
      ],
      "artists": [
        {
          "name": "Poppy",
          "appleUrl": null
        }
      ],
      "album": {
        "name": "Empty Hands",
        "releaseDate": null,
        "coverImage": "https://is1-ssl.mzstatic.com/image/thumb/Music211/v4/10/83/27/10832750-4df6-9ae1-5636-d01dae9c25e0/198704839702_Cover.jpg/600x600bb.jpg",
        "appleUrl": "https://music.apple.com/us/album/unravel/1852046141"
      },
      "durationMs": 175446,
      "explicit": false,
      "appleUrl": "https://music.apple.com/us/album/unravel/1852046141?i=1852046335",
      "appleId": "1852046335"
    },
    {
      "position": 49,
      "title": "Break Stuff",
      "artistNames": [
        "Limp Bizkit"
      ],
      "artists": [
        {
          "name": "Limp Bizkit",
          "appleUrl": null
        }
      ],
      "album": {
        "name": "Significant Other",
        "releaseDate": null,
        "coverImage": "https://is1-ssl.mzstatic.com/image/thumb/Music126/v4/54/2c/e5/542ce5e4-b086-c9a8-bef5-5be01b0dd025/06UMGIM01666.rgb.jpg/600x600bb.jpg",
        "appleUrl": "https://music.apple.com/us/album/break-stuff/1440754472"
      },
      "durationMs": 166707,
      "explicit": true,
      "appleUrl": "https://music.apple.com/us/album/break-stuff/1440754472?i=1440754477",
      "appleId": "1440754477"
    },
    {
      "position": 50,
      "title": "I Don't Care",
      "artistNames": [
        "Megadeth"
      ],
      "artists": [
        {
          "name": "Megadeth",
          "appleUrl": null
        }
      ],
      "album": {
        "name": "Megadeth",
        "releaseDate": null,
        "coverImage": "https://is1-ssl.mzstatic.com/image/thumb/Music221/v4/0d/cb/e5/0dcbe58e-d061-bcd2-0e2d-19b8a4dcde78/199538837193.jpg/600x600bb.jpg",
        "appleUrl": "https://music.apple.com/us/album/i-dont-care/1840222160"
      },
      "durationMs": 189915,
      "explicit": false,
      "appleUrl": "https://music.apple.com/us/album/i-dont-care/1840222160?i=1840222167",
      "appleId": "1840222167"
    },
    {
      "position": 51,
      "title": "Silent Divide",
      "artistNames": [
        "Alter Bridge"
      ],
      "artists": [
        {
          "name": "Alter Bridge",
          "appleUrl": null
        }
      ],
      "album": {
        "name": "Alter Bridge",
        "releaseDate": null,
        "coverImage": "https://is1-ssl.mzstatic.com/image/thumb/Music221/v4/73/4a/eb/734aeb4f-f75d-831a-f73a-3a743e350057/810185191963.jpg/600x600bb.jpg",
        "appleUrl": "https://music.apple.com/us/album/silent-divide/1831537883"
      },
      "durationMs": 303832,
      "explicit": false,
      "appleUrl": "https://music.apple.com/us/album/silent-divide/1831537883?i=1831537884",
      "appleId": "1831537884"
    },
    {
      "position": 52,
      "title": "You Give Love a Bad Name",
      "artistNames": [
        "Bon Jovi"
      ],
      "artists": [
        {
          "name": "Bon Jovi",
          "appleUrl": null
        }
      ],
      "album": {
        "name": "Slippery When Wet",
        "releaseDate": null,
        "coverImage": "https://is1-ssl.mzstatic.com/image/thumb/Music112/v4/40/16/3e/40163e24-6985-b785-d4ea-cbae07d74812/06UMGIM05422.rgb.jpg/600x600bb.jpg",
        "appleUrl": "https://music.apple.com/us/album/you-give-love-a-bad-name/1422954626"
      },
      "durationMs": 222644,
      "explicit": false,
      "appleUrl": "https://music.apple.com/us/album/you-give-love-a-bad-name/1422954626?i=1422954999",
      "appleId": "1422954999"
    },
    {
      "position": 53,
      "title": "Bruised Sky",
      "artistNames": [
        "Poppy"
      ],
      "artists": [
        {
          "name": "Poppy",
          "appleUrl": null
        }
      ],
      "album": {
        "name": "Empty Hands",
        "releaseDate": null,
        "coverImage": "https://is1-ssl.mzstatic.com/image/thumb/Music211/v4/10/83/27/10832750-4df6-9ae1-5636-d01dae9c25e0/198704839702_Cover.jpg/600x600bb.jpg",
        "appleUrl": "https://music.apple.com/us/album/bruised-sky/1852046141"
      },
      "durationMs": 220837,
      "explicit": false,
      "appleUrl": "https://music.apple.com/us/album/bruised-sky/1852046141?i=1852046145",
      "appleId": "1852046145"
    },
    {
      "position": 54,
      "title": "Blood and Tears",
      "artistNames": [
        "Danzig"
      ],
      "artists": [
        {
          "name": "Danzig",
          "appleUrl": null
        }
      ],
      "album": {
        "name": "Danzig II: Lucifuge",
        "releaseDate": null,
        "coverImage": "https://is1-ssl.mzstatic.com/image/thumb/Music118/v4/e4/6b/a6/e46ba611-6a19-cde3-33cc-eb300f646570/00602557176711.rgb.jpg/600x600bb.jpg",
        "appleUrl": "https://music.apple.com/us/album/blood-and-tears/1440885708"
      },
      "durationMs": 259794,
      "explicit": true,
      "appleUrl": "https://music.apple.com/us/album/blood-and-tears/1440885708?i=1440885835",
      "appleId": "1440885835"
    },
    {
      "position": 55,
      "title": "can u see me in the dark?",
      "artistNames": [
        "Halestorm & I Prevail"
      ],
      "artists": [
        {
          "name": "Halestorm & I Prevail",
          "appleUrl": null
        }
      ],
      "album": {
        "name": "can u see me in the dark? - Single",
        "releaseDate": null,
        "coverImage": "https://is1-ssl.mzstatic.com/image/thumb/Music211/v4/5d/20/39/5d2039b4-0fc7-e810-3fef-2c16ef7ca941/075679645333.jpg/600x600bb.jpg",
        "appleUrl": "https://music.apple.com/us/album/can-u-see-me-in-the-dark/1748191042"
      },
      "durationMs": 238756,
      "explicit": false,
      "appleUrl": "https://music.apple.com/us/album/can-u-see-me-in-the-dark/1748191042?i=1748191049",
      "appleId": "1748191049"
    },
    {
      "position": 56,
      "title": "Nobody's Fool",
      "artistNames": [
        "Cinderella"
      ],
      "artists": [
        {
          "name": "Cinderella",
          "appleUrl": null
        }
      ],
      "album": {
        "name": "Night Songs",
        "releaseDate": null,
        "coverImage": "https://is1-ssl.mzstatic.com/image/thumb/Music114/v4/d6/4f/06/d64f0679-5830-4558-1f1a-028af4446fad/06UMGIM07343.rgb.jpg/600x600bb.jpg",
        "appleUrl": "https://music.apple.com/us/album/nobodys-fool/1440494441"
      },
      "durationMs": 287400,
      "explicit": false,
      "appleUrl": "https://music.apple.com/us/album/nobodys-fool/1440494441?i=1440494451",
      "appleId": "1440494451"
    },
    {
      "position": 57,
      "title": "BLUR",
      "artistNames": [
        "Wage War"
      ],
      "artists": [
        {
          "name": "Wage War",
          "appleUrl": null
        }
      ],
      "album": {
        "name": "STIGMA",
        "releaseDate": null,
        "coverImage": "https://is1-ssl.mzstatic.com/image/thumb/Music221/v4/eb/9c/69/eb9c69d1-2178-6658-dc27-2025cd951fa1/24CRGIM41515.rgb.jpg/600x600bb.jpg",
        "appleUrl": "https://music.apple.com/us/album/blur/1735828489"
      },
      "durationMs": 181934,
      "explicit": false,
      "appleUrl": "https://music.apple.com/us/album/blur/1735828489?i=1735828506",
      "appleId": "1735828506"
    },
    {
      "position": 58,
      "title": "Paper Machete",
      "artistNames": [
        "Queens of the Stone Age"
      ],
      "artists": [
        {
          "name": "Queens of the Stone Age",
          "appleUrl": null
        }
      ],
      "album": {
        "name": "In Times New Roman...",
        "releaseDate": null,
        "coverImage": "https://is1-ssl.mzstatic.com/image/thumb/Music126/v4/3e/4f/c2/3e4fc24f-af10-4e63-0c2f-9c70dde347ea/191401194778.png/600x600bb.jpg",
        "appleUrl": "https://music.apple.com/us/album/paper-machete/1676853411"
      },
      "durationMs": 202777,
      "explicit": false,
      "appleUrl": "https://music.apple.com/us/album/paper-machete/1676853411?i=1676853528",
      "appleId": "1676853528"
    },
    {
      "position": 59,
      "title": "Yellow Roses",
      "artistNames": [
        "Highly Suspect"
      ],
      "artists": [
        {
          "name": "Highly Suspect",
          "appleUrl": null
        }
      ],
      "album": {
        "name": "Yellow Roses - Single",
        "releaseDate": null,
        "coverImage": "https://is1-ssl.mzstatic.com/image/thumb/Music221/v4/a7/e0/25/a7e025f9-7364-f67e-674e-b3d8f0a49700/193436460989_FAVE.jpg/600x600bb.jpg",
        "appleUrl": "https://music.apple.com/us/album/yellow-roses/1877113367"
      },
      "durationMs": 202758,
      "explicit": false,
      "appleUrl": "https://music.apple.com/us/album/yellow-roses/1877113367?i=1877113368",
      "appleId": "1877113368"
    },
    {
      "position": 60,
      "title": "In The Misery",
      "artistNames": [
        "The 69 Eyes"
      ],
      "artists": [
        {
          "name": "The 69 Eyes",
          "appleUrl": null
        }
      ],
      "album": {
        "name": "I Survive - EP",
        "releaseDate": null,
        "coverImage": "https://is1-ssl.mzstatic.com/image/thumb/Music211/v4/92/d4/9b/92d49be4-7a5a-8505-a369-650ff4be8f59/820200554086.jpg/600x600bb.jpg",
        "appleUrl": "https://music.apple.com/us/album/in-the-misery/1882874516"
      },
      "durationMs": 216194,
      "explicit": false,
      "appleUrl": "https://music.apple.com/us/album/in-the-misery/1882874516?i=1882874924",
      "appleId": "1882874924"
    },
    {
      "position": 61,
      "title": "Stinkfist",
      "artistNames": [
        "TOOL"
      ],
      "artists": [
        {
          "name": "TOOL",
          "appleUrl": null
        }
      ],
      "album": {
        "name": "Ænima",
        "releaseDate": null,
        "coverImage": "https://is1-ssl.mzstatic.com/image/thumb/Music113/v4/be/e3/59/bee35988-338f-f01a-6271-ceefdd3f8925/886447824757.jpg/600x600bb.jpg",
        "appleUrl": "https://music.apple.com/us/album/stinkfist/1474185335"
      },
      "durationMs": 311293,
      "explicit": false,
      "appleUrl": "https://music.apple.com/us/album/stinkfist/1474185335?i=1474185338",
      "appleId": "1474185338"
    },
    {
      "position": 62,
      "title": "I HATE ME TOO",
      "artistNames": [
        "Giovannie and the Hired Guns"
      ],
      "artists": [
        {
          "name": "Giovannie and the Hired Guns",
          "appleUrl": null
        }
      ],
      "album": {
        "name": "I HATE ME TOO - Single",
        "releaseDate": null,
        "coverImage": "https://is1-ssl.mzstatic.com/image/thumb/Music221/v4/79/6e/6d/796e6d36-5b99-78bf-34de-5d61f5e36913/199350814396.jpg/600x600bb.jpg",
        "appleUrl": "https://music.apple.com/us/album/i-hate-me-too/1817683328"
      },
      "durationMs": 185569,
      "explicit": true,
      "appleUrl": "https://music.apple.com/us/album/i-hate-me-too/1817683328?i=1817683329",
      "appleId": "1817683329"
    },
    {
      "position": 63,
      "title": "Zeit",
      "artistNames": [
        "Rammstein"
      ],
      "artists": [
        {
          "name": "Rammstein",
          "appleUrl": null
        }
      ],
      "album": {
        "name": "Zeit",
        "releaseDate": null,
        "coverImage": "https://is1-ssl.mzstatic.com/image/thumb/Music126/v4/4f/7e/43/4f7e43fd-3598-d2b2-e7b4-b9a69e998e25/21UM1IM29936.rgb.jpg/600x600bb.jpg",
        "appleUrl": "https://music.apple.com/us/album/zeit/1612051984"
      },
      "durationMs": 321687,
      "explicit": false,
      "appleUrl": "https://music.apple.com/us/album/zeit/1612051984?i=1612052142",
      "appleId": "1612052142"
    },
    {
      "position": 64,
      "title": "Bringin' On The Heartbreak (Remastered 2018)",
      "artistNames": [
        "Def Leppard"
      ],
      "artists": [
        {
          "name": "Def Leppard",
          "appleUrl": null
        }
      ],
      "album": {
        "name": "High 'N' Dry (Remastered 2018)",
        "releaseDate": null,
        "coverImage": "https://is1-ssl.mzstatic.com/image/thumb/Music124/v4/98/9d/2e/989d2e39-6077-b384-95b3-8f9f2ffc8744/19UMGIM77632.rgb.jpg/600x600bb.jpg",
        "appleUrl": "https://music.apple.com/us/album/bringin-on-the-heartbreak-remastered-2018/1501776925"
      },
      "durationMs": 273733,
      "explicit": false,
      "appleUrl": "https://music.apple.com/us/album/bringin-on-the-heartbreak-remastered-2018/1501776925?i=1501776932",
      "appleId": "1501776932"
    },
    {
      "position": 65,
      "title": "The Sound of Silence",
      "artistNames": [
        "Disturbed"
      ],
      "artists": [
        {
          "name": "Disturbed",
          "appleUrl": null
        }
      ],
      "album": {
        "name": "Immortalized (Deluxe Edition)",
        "releaseDate": null,
        "coverImage": "https://is1-ssl.mzstatic.com/image/thumb/Music125/v4/32/2b/12/322b1228-a133-3317-8d05-742669b700ec/093624926245.jpg/600x600bb.jpg",
        "appleUrl": "https://music.apple.com/us/album/the-sound-of-silence/1006937448"
      },
      "durationMs": 248487,
      "explicit": false,
      "appleUrl": "https://music.apple.com/us/album/the-sound-of-silence/1006937448?i=1006937459",
      "appleId": "1006937459"
    },
    {
      "position": 66,
      "title": "Don't Cry (Alternate Lyrics)",
      "artistNames": [
        "Guns N' Roses"
      ],
      "artists": [
        {
          "name": "Guns N' Roses",
          "appleUrl": null
        }
      ],
      "album": {
        "name": "Use Your Illusion II",
        "releaseDate": null,
        "coverImage": "https://is1-ssl.mzstatic.com/image/thumb/Music122/v4/db/8e/35/db8e356d-76e8-1e10-d7cb-87870bdbfad2/18UMGIM31437.rgb.jpg/600x600bb.jpg",
        "appleUrl": "https://music.apple.com/us/album/dont-cry-alternate-lyrics/1389971138"
      },
      "durationMs": 284267,
      "explicit": false,
      "appleUrl": "https://music.apple.com/us/album/dont-cry-alternate-lyrics/1389971138?i=1389971340",
      "appleId": "1389971340"
    },
    {
      "position": 67,
      "title": "Twisting The Knife (feat. Mckenna Grace)",
      "artistNames": [
        "ICE NINE KILLS"
      ],
      "artists": [
        {
          "name": "ICE NINE KILLS",
          "appleUrl": null
        }
      ],
      "album": {
        "name": "Twisting The Knife (feat. Mckenna Grace) - Single",
        "releaseDate": null,
        "coverImage": "https://is1-ssl.mzstatic.com/image/thumb/Music221/v4/63/cf/b5/63cfb5fd-e324-a6f2-85e9-650ac31eab92/ticket.zrbtimht.jpg/600x600bb.jpg",
        "appleUrl": "https://music.apple.com/us/album/twisting-the-knife-feat-mckenna-grace/1871023713"
      },
      "durationMs": 201478,
      "explicit": false,
      "appleUrl": "https://music.apple.com/us/album/twisting-the-knife-feat-mckenna-grace/1871023713?i=1871023730",
      "appleId": "1871023730"
    },
    {
      "position": 68,
      "title": "Something In The Way",
      "artistNames": [
        "Nirvana"
      ],
      "artists": [
        {
          "name": "Nirvana",
          "appleUrl": null
        }
      ],
      "album": {
        "name": "Nevermind",
        "releaseDate": null,
        "coverImage": "https://is1-ssl.mzstatic.com/image/thumb/Music115/v4/95/fd/b9/95fdb9b2-6d2b-92a6-97f2-51c1a6d77f1a/00602527874609.rgb.jpg/600x600bb.jpg",
        "appleUrl": "https://music.apple.com/us/album/something-in-the-way/1440783617"
      },
      "durationMs": 232183,
      "explicit": false,
      "appleUrl": "https://music.apple.com/us/album/something-in-the-way/1440783617?i=1440783790",
      "appleId": "1440783790"
    },
    {
      "position": 69,
      "title": "The Reason",
      "artistNames": [
        "Hoobastank"
      ],
      "artists": [
        {
          "name": "Hoobastank",
          "appleUrl": null
        }
      ],
      "album": {
        "name": "The Reason (20th Anniversary)",
        "releaseDate": null,
        "coverImage": "https://is1-ssl.mzstatic.com/image/thumb/Music126/v4/67/c6/73/67c67343-aa34-de98-19dd-017de2da775f/19UMGIM68930.rgb.jpg/600x600bb.jpg",
        "appleUrl": "https://music.apple.com/us/album/the-reason/1722839954"
      },
      "durationMs": 232800,
      "explicit": false,
      "appleUrl": "https://music.apple.com/us/album/the-reason/1722839954?i=1722840331",
      "appleId": "1722840331"
    },
    {
      "position": 70,
      "title": "Screaming",
      "artistNames": [
        "Loathe"
      ],
      "artists": [
        {
          "name": "Loathe",
          "appleUrl": null
        }
      ],
      "album": {
        "name": "I Let It in and It Took Everything",
        "releaseDate": null,
        "coverImage": "https://is1-ssl.mzstatic.com/image/thumb/Music123/v4/96/00/0d/96000d08-9403-fcfa-a865-178160a13313/cover.jpg/600x600bb.jpg",
        "appleUrl": "https://music.apple.com/us/album/screaming/1487438250"
      },
      "durationMs": 354640,
      "explicit": false,
      "appleUrl": "https://music.apple.com/us/album/screaming/1487438250?i=1487438787",
      "appleId": "1487438787"
    },
    {
      "position": 71,
      "title": "Terrible Lie",
      "artistNames": [
        "Nine Inch Nails"
      ],
      "artists": [
        {
          "name": "Nine Inch Nails",
          "appleUrl": null
        }
      ],
      "album": {
        "name": "Pretty Hate Machine (Remastered)",
        "releaseDate": null,
        "coverImage": "https://is1-ssl.mzstatic.com/image/thumb/Music125/v4/df/cf/84/dfcf8463-e753-5891-20d6-824749d220ca/00859704670275.rgb.jpg/600x600bb.jpg",
        "appleUrl": "https://music.apple.com/us/album/terrible-lie/1440940694"
      },
      "durationMs": 278720,
      "explicit": false,
      "appleUrl": "https://music.apple.com/us/album/terrible-lie/1440940694?i=1440941063",
      "appleId": "1440941063"
    },
    {
      "position": 72,
      "title": "Fell On Black Days",
      "artistNames": [
        "Soundgarden"
      ],
      "artists": [
        {
          "name": "Soundgarden",
          "appleUrl": null
        }
      ],
      "album": {
        "name": "Superunknown (20th Anniversary)",
        "releaseDate": null,
        "coverImage": "https://is1-ssl.mzstatic.com/image/thumb/Music221/v4/ae/b6/d6/aeb6d672-2004-41eb-ccba-e2964643a2bc/06UMGIM18607.rgb.jpg/600x600bb.jpg",
        "appleUrl": "https://music.apple.com/us/album/fell-on-black-days/1440811129"
      },
      "durationMs": 283027,
      "explicit": false,
      "appleUrl": "https://music.apple.com/us/album/fell-on-black-days/1440811129?i=1440811476",
      "appleId": "1440811476"
    },
    {
      "position": 73,
      "title": "Barely Breathing (feat. Against The Current)",
      "artistNames": [
        "From Ashes to New"
      ],
      "artists": [
        {
          "name": "From Ashes to New",
          "appleUrl": null
        }
      ],
      "album": {
        "name": "Barely Breathing (feat. Against The Current) - Single",
        "releaseDate": null,
        "coverImage": "https://is1-ssl.mzstatic.com/image/thumb/Music116/v4/c1/4a/92/c14a92be-e1ed-5d7c-63fd-7ec67b679bca/846070061103.png/600x600bb.jpg",
        "appleUrl": "https://music.apple.com/us/album/barely-breathing-feat-against-the-current/1721247249"
      },
      "durationMs": 190200,
      "explicit": true,
      "appleUrl": "https://music.apple.com/us/album/barely-breathing-feat-against-the-current/1721247249?i=1721247250",
      "appleId": "1721247250"
    },
    {
      "position": 74,
      "title": "Vore",
      "artistNames": [
        "Sleep Token"
      ],
      "artists": [
        {
          "name": "Sleep Token",
          "appleUrl": null
        }
      ],
      "album": {
        "name": "Take Me Back To Eden",
        "releaseDate": null,
        "coverImage": "https://is1-ssl.mzstatic.com/image/thumb/Music116/v4/e2/c6/0f/e2c60f68-7cec-fa08-6dd3-891aa72c247e/5401148000849_cover.jpg/600x600bb.jpg",
        "appleUrl": "https://music.apple.com/us/album/vore/1669567703"
      },
      "durationMs": 339607,
      "explicit": false,
      "appleUrl": "https://music.apple.com/us/album/vore/1669567703?i=1669568894",
      "appleId": "1669568894"
    },
    {
      "position": 75,
      "title": "Turn the Page",
      "artistNames": [
        "Metallica"
      ],
      "artists": [
        {
          "name": "Metallica",
          "appleUrl": null
        }
      ],
      "album": {
        "name": "Garage Inc.",
        "releaseDate": null,
        "coverImage": "https://is1-ssl.mzstatic.com/image/thumb/Music125/v4/ec/2f/09/ec2f0972-db2a-ef0d-52eb-7167fee36d5a/0075596229968.jpg/600x600bb.jpg",
        "appleUrl": "https://music.apple.com/us/album/turn-the-page/579370472"
      },
      "durationMs": 366573,
      "explicit": false,
      "appleUrl": "https://music.apple.com/us/album/turn-the-page/579370472?i=579370550",
      "appleId": "579370550"
    },
    {
      "position": 76,
      "title": "Don't Reach For Me",
      "artistNames": [
        "Knocked Loose"
      ],
      "artists": [
        {
          "name": "Knocked Loose",
          "appleUrl": null
        }
      ],
      "album": {
        "name": "You Won't Go Before You're Supposed To",
        "releaseDate": null,
        "coverImage": "https://is1-ssl.mzstatic.com/image/thumb/Music122/v4/53/d0/d0/53d0d0f1-c7d9-10d4-2b1a-f303ee950501/198391013393.jpg/600x600bb.jpg",
        "appleUrl": "https://music.apple.com/us/album/dont-reach-for-me/1732119298"
      },
      "durationMs": 225241,
      "explicit": true,
      "appleUrl": "https://music.apple.com/us/album/dont-reach-for-me/1732119298?i=1732119478",
      "appleId": "1732119478"
    },
    {
      "position": 77,
      "title": "Unravelling",
      "artistNames": [
        "Muse"
      ],
      "artists": [
        {
          "name": "Muse",
          "appleUrl": null
        }
      ],
      "album": {
        "name": "Unravelling - Single",
        "releaseDate": null,
        "coverImage": "https://is1-ssl.mzstatic.com/image/thumb/Music211/v4/ef/96/13/ef9613c9-2021-e542-c320-b372da733da2/5021732834430.jpg/600x600bb.jpg",
        "appleUrl": "https://music.apple.com/us/album/unravelling/1818597942"
      },
      "durationMs": 238002,
      "explicit": false,
      "appleUrl": "https://music.apple.com/us/album/unravelling/1818597942?i=1818597945",
      "appleId": "1818597945"
    },
    {
      "position": 78,
      "title": "Numb",
      "artistNames": [
        "LINKIN PARK"
      ],
      "artists": [
        {
          "name": "LINKIN PARK",
          "appleUrl": null
        }
      ],
      "album": {
        "name": "Meteora (Deluxe Edition)",
        "releaseDate": null,
        "coverImage": "https://is1-ssl.mzstatic.com/image/thumb/Music115/v4/13/44/05/134405bd-9e27-a678-8953-b5f724201f95/093624948988.jpg/600x600bb.jpg",
        "appleUrl": "https://music.apple.com/us/album/numb/590423275"
      },
      "durationMs": 187508,
      "explicit": false,
      "appleUrl": "https://music.apple.com/us/album/numb/590423275?i=590423552",
      "appleId": "590423552"
    },
    {
      "position": 79,
      "title": "I Remember You",
      "artistNames": [
        "Skid Row"
      ],
      "artists": [
        {
          "name": "Skid Row",
          "appleUrl": null
        }
      ],
      "album": {
        "name": "Skid Row (30th Anniversary Deluxe Edition)",
        "releaseDate": null,
        "coverImage": "https://is1-ssl.mzstatic.com/image/thumb/Music126/v4/4d/aa/b9/4daab977-e9be-8a2b-989e-1240aa0457f8/0603497852932.jpg/600x600bb.jpg",
        "appleUrl": "https://music.apple.com/us/album/i-remember-you/1727232035"
      },
      "durationMs": 314629,
      "explicit": false,
      "appleUrl": "https://music.apple.com/us/album/i-remember-you/1727232035?i=1727232565",
      "appleId": "1727232565"
    },
    {
      "position": 80,
      "title": "Six Feet Deep",
      "artistNames": [
        "The Warning"
      ],
      "artists": [
        {
          "name": "The Warning",
          "appleUrl": null
        }
      ],
      "album": {
        "name": "Keep Me Fed",
        "releaseDate": null,
        "coverImage": "https://is1-ssl.mzstatic.com/image/thumb/Music211/v4/21/4c/06/214c06c3-ded9-2f2c-17f1-b0f50dd56653/24UMGIM20617.rgb.jpg/600x600bb.jpg",
        "appleUrl": "https://music.apple.com/us/album/six-feet-deep/1733741692"
      },
      "durationMs": 179718,
      "explicit": false,
      "appleUrl": "https://music.apple.com/us/album/six-feet-deep/1733741692?i=1733741702",
      "appleId": "1733741702"
    },
    {
      "position": 81,
      "title": "In the End",
      "artistNames": [
        "LINKIN PARK"
      ],
      "artists": [
        {
          "name": "LINKIN PARK",
          "appleUrl": null
        }
      ],
      "album": {
        "name": "Hybrid Theory (Deluxe Edition)",
        "releaseDate": null,
        "coverImage": "https://is1-ssl.mzstatic.com/image/thumb/Music115/v4/53/a7/7f/53a77fab-c54c-a57b-8130-248fc12d0c80/093624948995.jpg/600x600bb.jpg",
        "appleUrl": "https://music.apple.com/us/album/in-the-end/590431776"
      },
      "durationMs": 216294,
      "explicit": false,
      "appleUrl": "https://music.apple.com/us/album/in-the-end/590431776?i=590431785",
      "appleId": "590431785"
    },
    {
      "position": 82,
      "title": "What It Takes",
      "artistNames": [
        "Aerosmith"
      ],
      "artists": [
        {
          "name": "Aerosmith",
          "appleUrl": null
        }
      ],
      "album": {
        "name": "Pump",
        "releaseDate": null,
        "coverImage": "https://is1-ssl.mzstatic.com/image/thumb/Music114/v4/65/92/0c/65920cae-e1e0-03ce-812e-70de7bb03f86/00602537156665.rgb.jpg/600x600bb.jpg",
        "appleUrl": "https://music.apple.com/us/album/what-it-takes/1440824301"
      },
      "durationMs": 387816,
      "explicit": false,
      "appleUrl": "https://music.apple.com/us/album/what-it-takes/1440824301?i=1440825033",
      "appleId": "1440825033"
    },
    {
      "position": 83,
      "title": "I Stay Away",
      "artistNames": [
        "Alice In Chains"
      ],
      "artists": [
        {
          "name": "Alice In Chains",
          "appleUrl": null
        }
      ],
      "album": {
        "name": "Jar of Flies - EP",
        "releaseDate": null,
        "coverImage": "https://is1-ssl.mzstatic.com/image/thumb/Music126/v4/bd/d6/37/bdd6373e-dc26-e86e-1d31-9bb1f7656968/5099747485527.jpg/600x600bb.jpg",
        "appleUrl": "https://music.apple.com/us/album/i-stay-away/268435274"
      },
      "durationMs": 254309,
      "explicit": false,
      "appleUrl": "https://music.apple.com/us/album/i-stay-away/268435274?i=268435302",
      "appleId": "268435302"
    },
    {
      "position": 84,
      "title": "Your Betrayal",
      "artistNames": [
        "Bullet for My Valentine"
      ],
      "artists": [
        {
          "name": "Bullet for My Valentine",
          "appleUrl": null
        }
      ],
      "album": {
        "name": "Fever (Tour Edition)",
        "releaseDate": null,
        "coverImage": "https://is1-ssl.mzstatic.com/image/thumb/Music124/v4/56/64/37/56643770-4b74-ec86-c671-8ad6a103d9c9/mzi.gaswxlvj.jpg/600x600bb.jpg",
        "appleUrl": "https://music.apple.com/us/album/your-betrayal/416870383"
      },
      "durationMs": 291427,
      "explicit": false,
      "appleUrl": "https://music.apple.com/us/album/your-betrayal/416870383?i=416870442",
      "appleId": "416870442"
    },
    {
      "position": 85,
      "title": "Every Rose Has Its Thorn",
      "artistNames": [
        "Poison"
      ],
      "artists": [
        {
          "name": "Poison",
          "appleUrl": null
        }
      ],
      "album": {
        "name": "Open Up and Say... Ahh! (20th Anniversary Edition)",
        "releaseDate": null,
        "coverImage": "https://is1-ssl.mzstatic.com/image/thumb/Music112/v4/6a/2a/1a/6a2a1a71-7a0e-75f5-026b-5017c69e53d7/13UABIM49846.rgb.jpg/600x600bb.jpg",
        "appleUrl": "https://music.apple.com/us/album/every-rose-has-its-thorn/716552394"
      },
      "durationMs": 260173,
      "explicit": false,
      "appleUrl": "https://music.apple.com/us/album/every-rose-has-its-thorn/716552394?i=716552556",
      "appleId": "716552556"
    },
    {
      "position": 86,
      "title": "Teardrops",
      "artistNames": [
        "Bring Me The Horizon"
      ],
      "artists": [
        {
          "name": "Bring Me The Horizon",
          "appleUrl": null
        }
      ],
      "album": {
        "name": "POST HUMAN: SURVIVAL HORROR",
        "releaseDate": null,
        "coverImage": "https://is1-ssl.mzstatic.com/image/thumb/Music211/v4/2a/00/ed/2a00ed34-47da-12fc-1444-15b895b3dd9e/886448602200.jpg/600x600bb.jpg",
        "appleUrl": "https://music.apple.com/us/album/teardrops/1535067172"
      },
      "durationMs": 215004,
      "explicit": true,
      "appleUrl": "https://music.apple.com/us/album/teardrops/1535067172?i=1535067183",
      "appleId": "1535067183"
    },
    {
      "position": 87,
      "title": "Last Resort",
      "artistNames": [
        "Papa Roach"
      ],
      "artists": [
        {
          "name": "Papa Roach",
          "appleUrl": null
        }
      ],
      "album": {
        "name": "Infest",
        "releaseDate": null,
        "coverImage": "https://is1-ssl.mzstatic.com/image/thumb/Music221/v4/14/1b/c7/141bc710-5495-7f17-67b8-b97395eed60b/18UMGIM85521.rgb.jpg/600x600bb.jpg",
        "appleUrl": "https://music.apple.com/us/album/last-resort/1450006102"
      },
      "durationMs": 199907,
      "explicit": true,
      "appleUrl": "https://music.apple.com/us/album/last-resort/1450006102?i=1450006105",
      "appleId": "1450006105"
    },
    {
      "position": 88,
      "title": "For I Am Death",
      "artistNames": [
        "The Pretty Reckless"
      ],
      "artists": [
        {
          "name": "The Pretty Reckless",
          "appleUrl": null
        }
      ],
      "album": {
        "name": "Dear God",
        "releaseDate": null,
        "coverImage": "https://is1-ssl.mzstatic.com/image/thumb/Music221/v4/7a/04/ed/7a04ed0c-b477-cf86-18a4-411db9c0c8b6/25CRGIM51366.rgb.jpg/600x600bb.jpg",
        "appleUrl": "https://music.apple.com/us/album/for-i-am-death/1878237662"
      },
      "durationMs": 219490,
      "explicit": false,
      "appleUrl": "https://music.apple.com/us/album/for-i-am-death/1878237662?i=1878237670",
      "appleId": "1878237670"
    },
    {
      "position": 89,
      "title": "Break the Silence",
      "artistNames": [
        "Nevertel & Sleep Theory"
      ],
      "artists": [
        {
          "name": "Nevertel & Sleep Theory",
          "appleUrl": null
        }
      ],
      "album": {
        "name": "Start Again",
        "releaseDate": null,
        "coverImage": "https://is1-ssl.mzstatic.com/image/thumb/Music211/v4/fa/e5/38/fae538df-1fd2-de71-b57e-b4ec4d52480e/0045778808960.png/600x600bb.jpg",
        "appleUrl": "https://music.apple.com/us/album/break-the-silence/1807793873"
      },
      "durationMs": 186054,
      "explicit": false,
      "appleUrl": "https://music.apple.com/us/album/break-the-silence/1807793873?i=1807793877",
      "appleId": "1807793877"
    },
    {
      "position": 90,
      "title": "Black",
      "artistNames": [
        "Pearl Jam"
      ],
      "artists": [
        {
          "name": "Pearl Jam",
          "appleUrl": null
        }
      ],
      "album": {
        "name": "Ten",
        "releaseDate": null,
        "coverImage": "https://is1-ssl.mzstatic.com/image/thumb/Music221/v4/e0/e1/7c/e0e17cf0-62e5-6312-f3df-2462960cc8f1/884977724745.jpg/600x600bb.jpg",
        "appleUrl": "https://music.apple.com/us/album/black/425465247"
      },
      "durationMs": 342653,
      "explicit": false,
      "appleUrl": "https://music.apple.com/us/album/black/425465247?i=425465351",
      "appleId": "425465351"
    },
    {
      "position": 91,
      "title": "Changes",
      "artistNames": [
        "Black Sabbath"
      ],
      "artists": [
        {
          "name": "Black Sabbath",
          "appleUrl": null
        }
      ],
      "album": {
        "name": "Black Sabbath, Vol. 4",
        "releaseDate": null,
        "coverImage": "https://is1-ssl.mzstatic.com/image/thumb/Music124/v4/65/68/ac/6568ace4-0c7a-6387-47ed-2f4c3411ff4d/075992725927.jpg/600x600bb.jpg",
        "appleUrl": "https://music.apple.com/us/album/changes/785242007"
      },
      "durationMs": 282497,
      "explicit": false,
      "appleUrl": "https://music.apple.com/us/album/changes/785242007?i=785242020",
      "appleId": "785242020"
    },
    {
      "position": 92,
      "title": "Hemorrhage (In My Hands)",
      "artistNames": [
        "Fuel"
      ],
      "artists": [
        {
          "name": "Fuel",
          "appleUrl": null
        }
      ],
      "album": {
        "name": "Something Like Human",
        "releaseDate": null,
        "coverImage": "https://is1-ssl.mzstatic.com/image/thumb/Features114/v4/5f/d8/af/5fd8afb9-d41b-7d94-6a1a-471739f50bcc/dj.ibxbhduu.jpg/600x600bb.jpg",
        "appleUrl": "https://music.apple.com/us/album/hemorrhage-in-my-hands/203911934"
      },
      "durationMs": 236797,
      "explicit": false,
      "appleUrl": "https://music.apple.com/us/album/hemorrhage-in-my-hands/203911934?i=203911976",
      "appleId": "203911976"
    },
    {
      "position": 93,
      "title": "Blood Sport",
      "artistNames": [
        "Sleep Token"
      ],
      "artists": [
        {
          "name": "Sleep Token",
          "appleUrl": null
        }
      ],
      "album": {
        "name": "Sundowning",
        "releaseDate": null,
        "coverImage": "https://is1-ssl.mzstatic.com/image/thumb/Music112/v4/8c/f0/bf/8cf0bf11-a801-808b-b30a-876add6929f9/5400863106744_cover.jpg/600x600bb.jpg",
        "appleUrl": "https://music.apple.com/us/album/blood-sport/1659199534"
      },
      "durationMs": 247200,
      "explicit": false,
      "appleUrl": "https://music.apple.com/us/album/blood-sport/1659199534?i=1659200340",
      "appleId": "1659200340"
    },
    {
      "position": 94,
      "title": "Specter",
      "artistNames": [
        "Bad Omens"
      ],
      "artists": [
        {
          "name": "Bad Omens",
          "appleUrl": null
        }
      ],
      "album": {
        "name": "Specter - Single",
        "releaseDate": null,
        "coverImage": "https://is1-ssl.mzstatic.com/image/thumb/Music221/v4/fe/a5/ab/fea5abb5-f8bb-a5be-6fc2-747e4a8068e0/198704657344_Cover.jpg/600x600bb.jpg",
        "appleUrl": "https://music.apple.com/us/album/specter/1831595384"
      },
      "durationMs": 274408,
      "explicit": false,
      "appleUrl": "https://music.apple.com/us/album/specter/1831595384?i=1831595386",
      "appleId": "1831595386"
    },
    {
      "position": 95,
      "title": "Without Me",
      "artistNames": [
        "Dayseeker"
      ],
      "artists": [
        {
          "name": "Dayseeker",
          "appleUrl": null
        }
      ],
      "album": {
        "name": "Dark Sun",
        "releaseDate": null,
        "coverImage": "https://is1-ssl.mzstatic.com/image/thumb/Music126/v4/38/38/a2/3838a2d0-346b-cdfb-c373-fcd1ad01417c/5400863134143_cover.jpg/600x600bb.jpg",
        "appleUrl": "https://music.apple.com/us/album/without-me/1676679882"
      },
      "durationMs": 224800,
      "explicit": true,
      "appleUrl": "https://music.apple.com/us/album/without-me/1676679882?i=1676680229",
      "appleId": "1676680229"
    },
    {
      "position": 96,
      "title": "Don't Know What You Got (Till It's Gone)",
      "artistNames": [
        "Cinderella"
      ],
      "artists": [
        {
          "name": "Cinderella",
          "appleUrl": null
        }
      ],
      "album": {
        "name": "Long Cold Winter",
        "releaseDate": null,
        "coverImage": "https://is1-ssl.mzstatic.com/image/thumb/Music125/v4/af/af/eb/afafeb4b-204b-d2c0-5cf3-a8c9d9c154f9/06UMGIM04832.rgb.jpg/600x600bb.jpg",
        "appleUrl": "https://music.apple.com/us/album/dont-know-what-you-got-till-its-gone/1434883206"
      },
      "durationMs": 354640,
      "explicit": false,
      "appleUrl": "https://music.apple.com/us/album/dont-know-what-you-got-till-its-gone/1434883206?i=1434883426",
      "appleId": "1434883426"
    },
    {
      "position": 97,
      "title": "Another Life",
      "artistNames": [
        "Motionless In White"
      ],
      "artists": [
        {
          "name": "Motionless In White",
          "appleUrl": null
        }
      ],
      "album": {
        "name": "Disguise",
        "releaseDate": null,
        "coverImage": "https://is1-ssl.mzstatic.com/image/thumb/Music125/v4/5d/50/0c/5d500c19-b6a5-769c-5961-524a5ffb37cc/016861740702.jpg/600x600bb.jpg",
        "appleUrl": "https://music.apple.com/us/album/another-life/1458937557"
      },
      "durationMs": 205394,
      "explicit": false,
      "appleUrl": "https://music.apple.com/us/album/another-life/1458937557?i=1458937565",
      "appleId": "1458937565"
    },
    {
      "position": 98,
      "title": "Rain",
      "artistNames": [
        "I Prevail"
      ],
      "artists": [
        {
          "name": "I Prevail",
          "appleUrl": null
        }
      ],
      "album": {
        "name": "Violent Nature",
        "releaseDate": null,
        "coverImage": "https://is1-ssl.mzstatic.com/image/thumb/Music221/v4/8f/e6/38/8fe638f3-e2d3-b8a0-c45f-52599ad6f6c1/25CRGIM49709.rgb.jpg/600x600bb.jpg",
        "appleUrl": "https://music.apple.com/us/album/rain/1821278576"
      },
      "durationMs": 203522,
      "explicit": false,
      "appleUrl": "https://music.apple.com/us/album/rain/1821278576?i=1821278588",
      "appleId": "1821278588"
    },
    {
      "position": 99,
      "title": "Cold",
      "artistNames": [
        "Crossfade"
      ],
      "artists": [
        {
          "name": "Crossfade",
          "appleUrl": null
        }
      ],
      "album": {
        "name": "Crossfade",
        "releaseDate": null,
        "coverImage": "https://is1-ssl.mzstatic.com/image/thumb/Music124/v4/de/65/df/de65dfbc-04be-43d3-d774-cad244c9bbea/mzi.aiukqtpj.jpg/600x600bb.jpg",
        "appleUrl": "https://music.apple.com/us/album/cold/187470617"
      },
      "durationMs": 194227,
      "explicit": false,
      "appleUrl": "https://music.apple.com/us/album/cold/187470617?i=187470715",
      "appleId": "187470715"
    },
    {
      "position": 100,
      "title": "I'd Do Anything for Love (But I Won't Do That)",
      "artistNames": [
        "Meat Loaf"
      ],
      "artists": [
        {
          "name": "Meat Loaf",
          "appleUrl": null
        }
      ],
      "album": {
        "name": "Bat Out of Hell II: Back Into Hell (Deluxe Edition)",
        "releaseDate": null,
        "coverImage": "https://is1-ssl.mzstatic.com/image/thumb/Music115/v4/ca/46/04/ca460464-b911-0fdb-ff1a-a5b735c22cfe/00008811281021.rgb.jpg/600x600bb.jpg",
        "appleUrl": "https://music.apple.com/us/album/id-do-anything-for-love-but-i-wont-do-that/1452850182"
      },
      "durationMs": 720515,
      "explicit": false,
      "appleUrl": "https://music.apple.com/us/album/id-do-anything-for-love-but-i-wont-do-that/1452850182?i=1452850188",
      "appleId": "1452850188"
    }
  ]
}
