{
  "schemaVersion": 1,
  "slug": "pl.f19f6b5be8474fe789e36a6242f6113e",
  "parentSlug": "premium-playlists",
  "title": "New Fire 🔥",
  "subtitle": "Recommended Playlist",
  "kind": "playlist",
  "coverImage": "https://is1-ssl.mzstatic.com/image/thumb/Features115/v4/60/6b/f5/606bf5dc-da26-267e-bfcb-508bc9b2538d/U0MtTVMtV1ctTmV3X0ZpcmVfX18tQURBTV9JRD0xMTI0NjQ5MzExLnBuZw.png/296x296SC.DN01.webp?l=en-US",
  "appleUrl": "https://music.apple.com/us/playlist/new-fire/pl.f19f6b5be8474fe789e36a6242f6113e",
  "appleId": "pl.f19f6b5be8474fe789e36a6242f6113e",
  "market": "US",
  "trackCount": 100,
  "updatedAt": "2026-07-21T11:12:33.528Z",
  "stale": false,
  "tracks": [
    {
      "position": 1,
      "title": "SIREN",
      "artistNames": [
        "Tierra Whack"
      ],
      "artists": [
        {
          "name": "Tierra Whack",
          "appleUrl": null
        }
      ],
      "album": {
        "name": "WHACK'S MUSEUM",
        "releaseDate": null,
        "coverImage": "https://is1-ssl.mzstatic.com/image/thumb/Music211/v4/93/18/ae/9318ae17-2d28-3d9d-78e8-42a1aa5b3f20/ticket.qlyqqwqm.jpg/600x600bb.jpg",
        "appleUrl": "https://music.apple.com/us/album/siren/6773954494"
      },
      "durationMs": 138557,
      "explicit": true,
      "appleUrl": "https://music.apple.com/us/album/siren/6773954494?i=6773954767",
      "appleId": "6773954767"
    },
    {
      "position": 2,
      "title": "Madonna",
      "artistNames": [
        "Namasenda"
      ],
      "artists": [
        {
          "name": "Namasenda",
          "appleUrl": null
        }
      ],
      "album": {
        "name": "Limbo",
        "releaseDate": null,
        "coverImage": "https://is1-ssl.mzstatic.com/image/thumb/Music211/v4/d8/b6/8c/d8b68c62-78e1-9ea5-cc04-59cd7dbbaac5/8721253846451.png/600x600bb.jpg",
        "appleUrl": "https://music.apple.com/us/album/madonna/1874845564"
      },
      "durationMs": 137493,
      "explicit": true,
      "appleUrl": "https://music.apple.com/us/album/madonna/1874845564?i=1874845567",
      "appleId": "1874845567"
    },
    {
      "position": 3,
      "title": "Sick Of Love (Mura Masa Remix)",
      "artistNames": [
        "Lykke Li & Mura Masa"
      ],
      "artists": [
        {
          "name": "Lykke Li & Mura Masa",
          "appleUrl": null
        }
      ],
      "album": {
        "name": "Sick Of Love (Mura Masa Remix) - Single",
        "releaseDate": null,
        "coverImage": "https://is1-ssl.mzstatic.com/image/thumb/Music211/v4/04/da/72/04da72dc-c0ad-4de2-8f3f-75811eb8f61f/823375218548_Cover.jpg/600x600bb.jpg",
        "appleUrl": "https://music.apple.com/us/album/sick-of-love-mura-masa-remix/6776672829"
      },
      "durationMs": 334079,
      "explicit": false,
      "appleUrl": "https://music.apple.com/us/album/sick-of-love-mura-masa-remix/6776672829?i=6776672835",
      "appleId": "6776672835"
    },
    {
      "position": 4,
      "title": "CPR (horsegiirL remix)",
      "artistNames": [
        "Wet Leg & horsegiirL"
      ],
      "artists": [
        {
          "name": "Wet Leg & horsegiirL",
          "appleUrl": null
        }
      ],
      "album": {
        "name": "moisturizer (deluxe)",
        "releaseDate": null,
        "coverImage": "https://is1-ssl.mzstatic.com/image/thumb/Music211/v4/75/9d/02/759d02aa-d298-a2c6-58fe-75a3d59dcfad/887835068067.png/600x600bb.jpg",
        "appleUrl": "https://music.apple.com/us/album/cpr-horsegiirl-remix/1896040298"
      },
      "durationMs": 202000,
      "explicit": false,
      "appleUrl": "https://music.apple.com/us/album/cpr-horsegiirl-remix/1896040298?i=6765695635",
      "appleId": "6765695635"
    },
    {
      "position": 5,
      "title": "Creatine",
      "artistNames": [
        "Channel Tres"
      ],
      "artists": [
        {
          "name": "Channel Tres",
          "appleUrl": null
        }
      ],
      "album": {
        "name": "Creatine - Single",
        "releaseDate": null,
        "coverImage": "https://is1-ssl.mzstatic.com/image/thumb/Music221/v4/16/e7/56/16e75652-5852-a2f5-8814-73ff30c0c175/820233698580.jpg/600x600bb.jpg",
        "appleUrl": "https://music.apple.com/us/album/creatine/6780623420"
      },
      "durationMs": 109783,
      "explicit": true,
      "appleUrl": "https://music.apple.com/us/album/creatine/6780623420?i=6780623424",
      "appleId": "6780623424"
    },
    {
      "position": 6,
      "title": "Midnight Sun (Girls Trip)",
      "artistNames": [
        "Zara Larsson & PinkPantheress"
      ],
      "artists": [
        {
          "name": "Zara Larsson & PinkPantheress",
          "appleUrl": null
        }
      ],
      "album": {
        "name": "Midnight Sun: Girls Trip",
        "releaseDate": null,
        "coverImage": "https://is1-ssl.mzstatic.com/image/thumb/Music221/v4/82/77/00/82770034-e6df-9f5d-fe44-5697ed49caf6/196874257296.jpg/600x600bb.jpg",
        "appleUrl": "https://music.apple.com/us/album/midnight-sun-girls-trip/1894058251"
      },
      "durationMs": 171737,
      "explicit": false,
      "appleUrl": "https://music.apple.com/us/album/midnight-sun-girls-trip/1894058251?i=1894058258",
      "appleId": "1894058258"
    },
    {
      "position": 7,
      "title": "BE WHAT I WANT (feat. Paris Texas)",
      "artistNames": [
        "Kenny Mason"
      ],
      "artists": [
        {
          "name": "Kenny Mason",
          "appleUrl": null
        }
      ],
      "album": {
        "name": "BULLDAWG",
        "releaseDate": null,
        "coverImage": "https://is1-ssl.mzstatic.com/image/thumb/Music211/v4/62/04/dd/6204dd33-4696-79a8-b514-cc05f2f19823/075679581679.jpg/600x600bb.jpg",
        "appleUrl": "https://music.apple.com/us/album/be-what-i-want-feat-paris-texas/1894315301"
      },
      "durationMs": 221987,
      "explicit": true,
      "appleUrl": "https://music.apple.com/us/album/be-what-i-want-feat-paris-texas/1894315301?i=1894315315",
      "appleId": "1894315315"
    },
    {
      "position": 8,
      "title": "Knight In Shining Prada",
      "artistNames": [
        "Overmono & John Joseph Holt"
      ],
      "artists": [
        {
          "name": "Overmono & John Joseph Holt",
          "appleUrl": null
        }
      ],
      "album": {
        "name": "Pure Devotion",
        "releaseDate": null,
        "coverImage": "https://is1-ssl.mzstatic.com/image/thumb/Music211/v4/6a/cd/25/6acd2504-b1ef-8988-8fe0-240a5a25e0bc/191404166871.png/600x600bb.jpg",
        "appleUrl": "https://music.apple.com/us/album/knight-in-shining-prada/1894298100"
      },
      "durationMs": 257035,
      "explicit": false,
      "appleUrl": "https://music.apple.com/us/album/knight-in-shining-prada/1894298100?i=1894298106",
      "appleId": "1894298106"
    },
    {
      "position": 9,
      "title": "PQC (Bassvictim Edit)",
      "artistNames": [
        "daine & bassvictim"
      ],
      "artists": [
        {
          "name": "daine & bassvictim",
          "appleUrl": null
        }
      ],
      "album": {
        "name": "PQC (Bassvictim Edit) - Single",
        "releaseDate": null,
        "coverImage": "https://is1-ssl.mzstatic.com/image/thumb/Music211/v4/75/88/3c/75883c59-876e-e2a4-b058-58ffc8a9f3c3/612891064629.jpg/600x600bb.jpg",
        "appleUrl": "https://music.apple.com/us/album/pqc-bassvictim-edit/6776397010"
      },
      "durationMs": 211000,
      "explicit": false,
      "appleUrl": "https://music.apple.com/us/album/pqc-bassvictim-edit/6776397010?i=6776397011",
      "appleId": "6776397011"
    },
    {
      "position": 10,
      "title": "On Your Mind",
      "artistNames": [
        "FKA twigs & Lil Yachty"
      ],
      "artists": [
        {
          "name": "FKA twigs & Lil Yachty",
          "appleUrl": null
        }
      ],
      "album": {
        "name": "On Your Mind - Single",
        "releaseDate": null,
        "coverImage": "https://is1-ssl.mzstatic.com/image/thumb/Music221/v4/33/3a/1d/333a1ded-7738-80df-52c3-0f406d42c09c/075679575012.jpg/600x600bb.jpg",
        "appleUrl": "https://music.apple.com/us/album/on-your-mind/6781433175"
      },
      "durationMs": 217960,
      "explicit": false,
      "appleUrl": "https://music.apple.com/us/album/on-your-mind/6781433175?i=6781433176",
      "appleId": "6781433176"
    },
    {
      "position": 11,
      "title": "dancefloor?",
      "artistNames": [
        "bartek turski & kurtis baker"
      ],
      "artists": [
        {
          "name": "bartek turski & kurtis baker",
          "appleUrl": null
        }
      ],
      "album": {
        "name": "dancefloor? - Single",
        "releaseDate": null,
        "coverImage": "https://is1-ssl.mzstatic.com/image/thumb/Music211/v4/d6/5a/ce/d65ace15-8ffc-df68-19a7-b25985ee4ae3/7333591080377.jpg/600x600bb.jpg",
        "appleUrl": "https://music.apple.com/us/album/dancefloor/6787102157"
      },
      "durationMs": 201688,
      "explicit": false,
      "appleUrl": "https://music.apple.com/us/album/dancefloor/6787102157?i=6787102158",
      "appleId": "6787102158"
    },
    {
      "position": 12,
      "title": "R.I.P Peace",
      "artistNames": [
        "Liim"
      ],
      "artists": [
        {
          "name": "Liim",
          "appleUrl": null
        }
      ],
      "album": {
        "name": "R.I.P Peace - Single",
        "releaseDate": null,
        "coverImage": "https://is1-ssl.mzstatic.com/image/thumb/Music221/v4/0a/05/5b/0a055b9f-3d1f-ea05-1098-724cb5693d56/823191227441_cover.jpg/600x600bb.jpg",
        "appleUrl": "https://music.apple.com/us/album/r-i-p-peace/1895779606"
      },
      "durationMs": 175680,
      "explicit": true,
      "appleUrl": "https://music.apple.com/us/album/r-i-p-peace/1895779606?i=6764435521",
      "appleId": "6764435521"
    },
    {
      "position": 13,
      "title": "Thing About You",
      "artistNames": [
        "Two Shell"
      ],
      "artists": [
        {
          "name": "Two Shell",
          "appleUrl": null
        }
      ],
      "album": {
        "name": "Infinite Now",
        "releaseDate": null,
        "coverImage": "https://is1-ssl.mzstatic.com/image/thumb/Music211/v4/1b/fe/7a/1bfe7a88-cfda-0265-6b2b-e8a335440b57/889030050977.png/600x600bb.jpg",
        "appleUrl": "https://music.apple.com/us/album/thing-about-you/6771447672"
      },
      "durationMs": 269600,
      "explicit": false,
      "appleUrl": "https://music.apple.com/us/album/thing-about-you/6771447672?i=6771448144",
      "appleId": "6771448144"
    },
    {
      "position": 14,
      "title": "espiral",
      "artistNames": [
        "Ela Minus & Nick León"
      ],
      "artists": [
        {
          "name": "Ela Minus & Nick León",
          "appleUrl": null
        }
      ],
      "album": {
        "name": "qué les pasó a mis amigos? - Single",
        "releaseDate": null,
        "coverImage": "https://is1-ssl.mzstatic.com/image/thumb/Music221/v4/cb/41/9a/cb419a4c-968d-05e5-aa03-0fc00118f485/192152051266.png/600x600bb.jpg",
        "appleUrl": "https://music.apple.com/us/album/espiral/6777140036"
      },
      "durationMs": 219016,
      "explicit": false,
      "appleUrl": "https://music.apple.com/us/album/espiral/6777140036?i=6777140039",
      "appleId": "6777140039"
    },
    {
      "position": 15,
      "title": "99 Dimensional",
      "artistNames": [
        "Marci"
      ],
      "artists": [
        {
          "name": "Marci",
          "appleUrl": null
        }
      ],
      "album": {
        "name": "Mask Lady and Late Night Girl",
        "releaseDate": null,
        "coverImage": "https://is1-ssl.mzstatic.com/image/thumb/Music221/v4/26/52/cd/2652cdb3-7e89-2495-9925-e47253f7fbfe/66682.jpg/600x600bb.jpg",
        "appleUrl": "https://music.apple.com/us/album/99-dimensional/6768337128"
      },
      "durationMs": 164307,
      "explicit": false,
      "appleUrl": "https://music.apple.com/us/album/99-dimensional/6768337128?i=6768337435",
      "appleId": "6768337435"
    },
    {
      "position": 16,
      "title": "BIG DOG",
      "artistNames": [
        "Genesis Owusu"
      ],
      "artists": [
        {
          "name": "Genesis Owusu",
          "appleUrl": null
        }
      ],
      "album": {
        "name": "REDSTAR WU & THE WORLDWIDE SCOURGE",
        "releaseDate": null,
        "coverImage": "https://is1-ssl.mzstatic.com/image/thumb/Music221/v4/31/6e/cf/316ecf81-83aa-2da6-f65d-a2a1bdab4274/cover.jpg/600x600bb.jpg",
        "appleUrl": "https://music.apple.com/us/album/big-dog/1887196431"
      },
      "durationMs": 216312,
      "explicit": true,
      "appleUrl": "https://music.apple.com/us/album/big-dog/1887196431?i=1887197046",
      "appleId": "1887197046"
    },
    {
      "position": 17,
      "title": "THAT GUY",
      "artistNames": [
        "Tyler, The Creator"
      ],
      "artists": [
        {
          "name": "Tyler, The Creator",
          "appleUrl": null
        }
      ],
      "album": {
        "name": "THAT GUY - Single",
        "releaseDate": null,
        "coverImage": "https://is1-ssl.mzstatic.com/image/thumb/Music221/v4/51/7b/ed/517bed4e-17e5-993a-9e51-c2c520331de1/196874532515.jpg/600x600bb.jpg",
        "appleUrl": "https://music.apple.com/us/album/that-guy/6781040566"
      },
      "durationMs": 167533,
      "explicit": true,
      "appleUrl": "https://music.apple.com/us/album/that-guy/6781040566?i=6781040568",
      "appleId": "6781040568"
    },
    {
      "position": 18,
      "title": "Dis-le",
      "artistNames": [
        "Angèle"
      ],
      "artists": [
        {
          "name": "Angèle",
          "appleUrl": null
        }
      ],
      "album": {
        "name": "Dis-le - Single",
        "releaseDate": null,
        "coverImage": "https://is1-ssl.mzstatic.com/image/thumb/Music221/v4/63/e2/94/63e294d4-24fb-4b6d-5a0b-a8b69571c899/196874501719.jpg/600x600bb.jpg",
        "appleUrl": "https://music.apple.com/us/album/dis-le/6777024995"
      },
      "durationMs": 247459,
      "explicit": false,
      "appleUrl": "https://music.apple.com/us/album/dis-le/6777024995?i=6777024997",
      "appleId": "6777024997"
    },
    {
      "position": 19,
      "title": "Beyond The Brilliant Haze",
      "artistNames": [
        "Everything Is Recorded, Peter Gabriel & IDK"
      ],
      "artists": [
        {
          "name": "Everything Is Recorded, Peter Gabriel & IDK",
          "appleUrl": null
        }
      ],
      "album": {
        "name": "Beyond The Brilliant Haze - Single",
        "releaseDate": null,
        "coverImage": "https://is1-ssl.mzstatic.com/image/thumb/Music221/v4/34/e2/c1/34e2c18a-98bf-c6b8-9df1-ef243e892e85/191404165973.png/600x600bb.jpg",
        "appleUrl": "https://music.apple.com/us/album/beyond-the-brilliant-haze/6771369774"
      },
      "durationMs": 191800,
      "explicit": false,
      "appleUrl": "https://music.apple.com/us/album/beyond-the-brilliant-haze/6771369774?i=6771369776",
      "appleId": "6771369776"
    },
    {
      "position": 20,
      "title": "Hollywood Forever",
      "artistNames": [
        "underscores"
      ],
      "artists": [
        {
          "name": "underscores",
          "appleUrl": null
        }
      ],
      "album": {
        "name": "U",
        "releaseDate": null,
        "coverImage": "https://is1-ssl.mzstatic.com/image/thumb/Music211/v4/34/e9/68/34e9680c-152b-9fc6-07e7-8f253e76d8f2/810090098852_Cover.jpg/600x600bb.jpg",
        "appleUrl": "https://music.apple.com/us/album/hollywood-forever/1878382378"
      },
      "durationMs": 294857,
      "explicit": true,
      "appleUrl": "https://music.apple.com/us/album/hollywood-forever/1878382378?i=1878382599",
      "appleId": "1878382599"
    },
    {
      "position": 21,
      "title": "mi amor",
      "artistNames": [
        "88rising & Chini Tacchini"
      ],
      "artists": [
        {
          "name": "88rising & Chini Tacchini",
          "appleUrl": null
        }
      ],
      "album": {
        "name": "mi amor - Single",
        "releaseDate": null,
        "coverImage": "https://is1-ssl.mzstatic.com/image/thumb/Music211/v4/4c/c7/3b/4cc73b2d-ea77-f1c5-4484-ae474998b6d1/820233456098.jpg/600x600bb.jpg",
        "appleUrl": "https://music.apple.com/us/album/mi-amor/6773489201"
      },
      "durationMs": 97783,
      "explicit": false,
      "appleUrl": "https://music.apple.com/us/album/mi-amor/6773489201?i=6773489206",
      "appleId": "6773489206"
    },
    {
      "position": 22,
      "title": "Super Platinum (feat. Erick the Architect)",
      "artistNames": [
        "Madeon"
      ],
      "artists": [
        {
          "name": "Madeon",
          "appleUrl": null
        }
      ],
      "album": {
        "name": "Victory",
        "releaseDate": null,
        "coverImage": "https://is1-ssl.mzstatic.com/image/thumb/Music221/v4/4a/65/47/4a6547ba-962f-4352-b661-0e82505429f4/810090099071_Cover.jpg/600x600bb.jpg",
        "appleUrl": "https://music.apple.com/us/album/super-platinum-feat-erick-the-architect/1892422364"
      },
      "durationMs": 151569,
      "explicit": false,
      "appleUrl": "https://music.apple.com/us/album/super-platinum-feat-erick-the-architect/1892422364?i=1892422370",
      "appleId": "1892422370"
    },
    {
      "position": 23,
      "title": "Fire on the Water",
      "artistNames": [
        "Bonobo & Arooj Aftab"
      ],
      "artists": [
        {
          "name": "Bonobo & Arooj Aftab",
          "appleUrl": null
        }
      ],
      "album": {
        "name": "Distance in Static",
        "releaseDate": null,
        "coverImage": "https://is1-ssl.mzstatic.com/image/thumb/Music221/v4/8d/7d/5e/8d7d5e2a-31a9-50ba-9e04-3ce2b53d0c8c/5054429211276.png/600x600bb.jpg",
        "appleUrl": "https://music.apple.com/us/album/fire-on-the-water/1895659203"
      },
      "durationMs": 183048,
      "explicit": false,
      "appleUrl": "https://music.apple.com/us/album/fire-on-the-water/1895659203?i=6764144805",
      "appleId": "6764144805"
    },
    {
      "position": 24,
      "title": "Get F****d",
      "artistNames": [
        "Chalk"
      ],
      "artists": [
        {
          "name": "Chalk",
          "appleUrl": null
        }
      ],
      "album": {
        "name": "Get F****d - Single",
        "releaseDate": null,
        "coverImage": "https://is1-ssl.mzstatic.com/image/thumb/Music211/v4/ea/fd/18/eafd18fd-edab-2ded-8ea9-50483dc9b3d9/8721555480643.png/600x600bb.jpg",
        "appleUrl": "https://music.apple.com/us/album/get-f-d/6780525134"
      },
      "durationMs": 230141,
      "explicit": true,
      "appleUrl": "https://music.apple.com/us/album/get-f-d/6780525134?i=6780525135",
      "appleId": "6780525135"
    },
    {
      "position": 25,
      "title": "Lemon",
      "artistNames": [
        "Daniel Avery"
      ],
      "artists": [
        {
          "name": "Daniel Avery",
          "appleUrl": null
        }
      ],
      "album": {
        "name": "Lemon - Single",
        "releaseDate": null,
        "coverImage": "https://is1-ssl.mzstatic.com/image/thumb/Music221/v4/8c/1f/37/8c1f37f6-37fc-0ca5-33af-b00722e92ab3/887829000189.png/600x600bb.jpg",
        "appleUrl": "https://music.apple.com/us/album/lemon/6767566425"
      },
      "durationMs": 305813,
      "explicit": false,
      "appleUrl": "https://music.apple.com/us/album/lemon/6767566425?i=6767566430",
      "appleId": "6767566430"
    },
    {
      "position": 26,
      "title": "White Flag",
      "artistNames": [
        "Vince Staples"
      ],
      "artists": [
        {
          "name": "Vince Staples",
          "appleUrl": null
        }
      ],
      "album": {
        "name": "Cry Baby",
        "releaseDate": null,
        "coverImage": "https://is1-ssl.mzstatic.com/image/thumb/Music211/v4/27/fe/3c/27fe3ccb-9f3c-1472-a2af-ddabe248699b/26CRGIM53564.rgb.jpg/600x600bb.jpg",
        "appleUrl": "https://music.apple.com/us/album/white-flag/1887627836"
      },
      "durationMs": 154480,
      "explicit": true,
      "appleUrl": "https://music.apple.com/us/album/white-flag/1887627836?i=1887627840",
      "appleId": "1887627840"
    },
    {
      "position": 27,
      "title": "Only Love (feat. Pa Salieu)",
      "artistNames": [
        "Ezra Collective"
      ],
      "artists": [
        {
          "name": "Ezra Collective",
          "appleUrl": null
        }
      ],
      "album": {
        "name": "Here Because of Hope",
        "releaseDate": null,
        "coverImage": "https://is1-ssl.mzstatic.com/image/thumb/Music221/v4/af/84/ba/af84ba41-bcb5-0002-26b6-0647fee2272e/0720841306900_Cover.jpg/600x600bb.jpg",
        "appleUrl": "https://music.apple.com/us/album/only-love-feat-pa-salieu/6767014278"
      },
      "durationMs": 202546,
      "explicit": false,
      "appleUrl": "https://music.apple.com/us/album/only-love-feat-pa-salieu/6767014278?i=6767014290",
      "appleId": "6767014290"
    },
    {
      "position": 28,
      "title": "Body Office",
      "artistNames": [
        "Decius"
      ],
      "artists": [
        {
          "name": "Decius",
          "appleUrl": null
        }
      ],
      "album": {
        "name": "Decius Trax EP VII - Single",
        "releaseDate": null,
        "coverImage": "https://is1-ssl.mzstatic.com/image/thumb/Music211/v4/1e/61/70/1e6170cb-2af1-af54-342d-b2d169f953e7/5065003719392_cover.jpg/600x600bb.jpg",
        "appleUrl": "https://music.apple.com/us/album/body-office/6771906585"
      },
      "durationMs": 400266,
      "explicit": false,
      "appleUrl": "https://music.apple.com/us/album/body-office/6771906585?i=6771906599",
      "appleId": "6771906599"
    },
    {
      "position": 29,
      "title": "LOVE ME HATE ME",
      "artistNames": [
        "Six Sex"
      ],
      "artists": [
        {
          "name": "Six Sex",
          "appleUrl": null
        }
      ],
      "album": {
        "name": "ULTRA",
        "releaseDate": null,
        "coverImage": "https://is1-ssl.mzstatic.com/image/thumb/Music211/v4/e4/90/5b/e4905b95-46fa-fd79-e0ba-fbd5d47320f3/820233386944.jpg/600x600bb.jpg",
        "appleUrl": "https://music.apple.com/us/album/love-me-hate-me/6769903456"
      },
      "durationMs": 159314,
      "explicit": true,
      "appleUrl": "https://music.apple.com/us/album/love-me-hate-me/6769903456?i=6769903614",
      "appleId": "6769903614"
    },
    {
      "position": 30,
      "title": "Uyu 1",
      "artistNames": [
        "Nu Fvnk"
      ],
      "artists": [
        {
          "name": "Nu Fvnk",
          "appleUrl": null
        }
      ],
      "album": {
        "name": "KICK UYU",
        "releaseDate": null,
        "coverImage": "https://is1-ssl.mzstatic.com/image/thumb/Music211/v4/50/8a/b1/508ab178-b454-4e05-2869-87bebb3a456f/5059449364223.png/600x600bb.jpg",
        "appleUrl": "https://music.apple.com/us/album/uyu-1/6786337749"
      },
      "durationMs": 181278,
      "explicit": false,
      "appleUrl": "https://music.apple.com/us/album/uyu-1/6786337749?i=6786337750",
      "appleId": "6786337750"
    },
    {
      "position": 31,
      "title": "Molly In The Club",
      "artistNames": [
        "Sophia Stel"
      ],
      "artists": [
        {
          "name": "Sophia Stel",
          "appleUrl": null
        }
      ],
      "album": {
        "name": "Molly In The Club - Single",
        "releaseDate": null,
        "coverImage": "https://is1-ssl.mzstatic.com/image/thumb/Music211/v4/98/ed/81/98ed8113-67e4-6b84-b54d-b35248c0e14c/823375198369_Cover.jpg/600x600bb.jpg",
        "appleUrl": "https://music.apple.com/us/album/molly-in-the-club/6773161323"
      },
      "durationMs": 216138,
      "explicit": false,
      "appleUrl": "https://music.apple.com/us/album/molly-in-the-club/6773161323?i=6773161324",
      "appleId": "6773161324"
    },
    {
      "position": 32,
      "title": "that's my beach!",
      "artistNames": [
        "horsegiirL"
      ],
      "artists": [
        {
          "name": "horsegiirL",
          "appleUrl": null
        }
      ],
      "album": {
        "name": "NATURE IS HEALING",
        "releaseDate": null,
        "coverImage": "https://is1-ssl.mzstatic.com/image/thumb/Music221/v4/75/e2/7f/75e27f2f-0262-df4f-4e2b-501e94a22152/196874053829.jpg/600x600bb.jpg",
        "appleUrl": "https://music.apple.com/us/album/thats-my-beach/1893373426"
      },
      "durationMs": 198750,
      "explicit": true,
      "appleUrl": "https://music.apple.com/us/album/thats-my-beach/1893373426?i=1893373637",
      "appleId": "1893373637"
    },
    {
      "position": 33,
      "title": "What's Done Is Done",
      "artistNames": [
        "Jorja Smith"
      ],
      "artists": [
        {
          "name": "Jorja Smith",
          "appleUrl": null
        }
      ],
      "album": {
        "name": "What's Done Is Done - Single",
        "releaseDate": null,
        "coverImage": "https://is1-ssl.mzstatic.com/image/thumb/Music211/v4/dc/cf/11/dccf1138-2cdb-de58-14c2-1ef41f6a23f5/820233148306.jpg/600x600bb.jpg",
        "appleUrl": "https://music.apple.com/us/album/whats-done-is-done/1895156626"
      },
      "durationMs": 173022,
      "explicit": false,
      "appleUrl": "https://music.apple.com/us/album/whats-done-is-done/1895156626?i=6763088629",
      "appleId": "6763088629"
    },
    {
      "position": 34,
      "title": "Tracksuit",
      "artistNames": [
        "Maz"
      ],
      "artists": [
        {
          "name": "Maz",
          "appleUrl": null
        }
      ],
      "album": {
        "name": "Tracksuit - Single",
        "releaseDate": null,
        "coverImage": "https://is1-ssl.mzstatic.com/image/thumb/Music211/v4/ca/d1/99/cad199db-b04b-4246-e9c8-959909cdf013/66817.jpg/600x600bb.jpg",
        "appleUrl": "https://music.apple.com/us/album/tracksuit/1895152827"
      },
      "durationMs": 158785,
      "explicit": false,
      "appleUrl": "https://music.apple.com/us/album/tracksuit/1895152827?i=6763079722",
      "appleId": "6763079722"
    },
    {
      "position": 35,
      "title": "Eastside Girls",
      "artistNames": [
        "MUNA"
      ],
      "artists": [
        {
          "name": "MUNA",
          "appleUrl": null
        }
      ],
      "album": {
        "name": "Dancing On The Wall",
        "releaseDate": null,
        "coverImage": "https://is1-ssl.mzstatic.com/image/thumb/Music211/v4/27/24/4a/27244aaf-dd91-be23-a13a-b092c1f56010/61705.jpg/600x600bb.jpg",
        "appleUrl": "https://music.apple.com/us/album/eastside-girls/1870702692"
      },
      "durationMs": 230573,
      "explicit": true,
      "appleUrl": "https://music.apple.com/us/album/eastside-girls/1870702692?i=1870703307",
      "appleId": "1870703307"
    },
    {
      "position": 36,
      "title": "Ne Plus Ultra",
      "artistNames": [
        "ear"
      ],
      "artists": [
        {
          "name": "ear",
          "appleUrl": null
        }
      ],
      "album": {
        "name": "Ne Plus Ultra - Single",
        "releaseDate": null,
        "coverImage": "https://is1-ssl.mzstatic.com/image/thumb/Music221/v4/f6/6b/74/f66b7445-8f07-04b6-35e9-6fb1cba60313/823375155768_Cover.jpg/600x600bb.jpg",
        "appleUrl": "https://music.apple.com/us/album/ne-plus-ultra/1895982136"
      },
      "durationMs": 169286,
      "explicit": false,
      "appleUrl": "https://music.apple.com/us/album/ne-plus-ultra/1895982136?i=6765530891",
      "appleId": "6765530891"
    },
    {
      "position": 37,
      "title": "CLIMAX",
      "artistNames": [
        "12k Gotti"
      ],
      "artists": [
        {
          "name": "12k Gotti",
          "appleUrl": null
        }
      ],
      "album": {
        "name": "MADLIFE",
        "releaseDate": null,
        "coverImage": "https://is1-ssl.mzstatic.com/image/thumb/Music221/v4/09/f0/df/09f0df43-6324-f0db-ccbb-bf17ed53ce1e/5056818810275.png/600x600bb.jpg",
        "appleUrl": "https://music.apple.com/us/album/climax/6780874748"
      },
      "durationMs": 126955,
      "explicit": true,
      "appleUrl": "https://music.apple.com/us/album/climax/6780874748?i=6780874749",
      "appleId": "6780874749"
    },
    {
      "position": 38,
      "title": "Whispers",
      "artistNames": [
        "Jelani Blackman, WHOOSH & MULIMBA"
      ],
      "artists": [
        {
          "name": "Jelani Blackman, WHOOSH & MULIMBA",
          "appleUrl": null
        }
      ],
      "album": {
        "name": "Whispers - Single",
        "releaseDate": null,
        "coverImage": "https://is1-ssl.mzstatic.com/image/thumb/Music221/v4/4f/b2/f6/4fb2f6e7-bab0-9cae-5452-812d056bbe37/5063961616487_cover.jpg/600x600bb.jpg",
        "appleUrl": "https://music.apple.com/us/album/whispers/6773864928"
      },
      "durationMs": 157573,
      "explicit": false,
      "appleUrl": "https://music.apple.com/us/album/whispers/6773864928?i=6773865449",
      "appleId": "6773865449"
    },
    {
      "position": 39,
      "title": "a la mala",
      "artistNames": [
        "Bb trickz"
      ],
      "artists": [
        {
          "name": "Bb trickz",
          "appleUrl": null
        }
      ],
      "album": {
        "name": "a la mala - Single",
        "releaseDate": null,
        "coverImage": "https://is1-ssl.mzstatic.com/image/thumb/Music221/v4/76/44/b9/7644b934-9dab-bf21-da16-1540900ebb12/196874427590.jpg/600x600bb.jpg",
        "appleUrl": "https://music.apple.com/us/album/a-la-mala/6773419416"
      },
      "durationMs": 91288,
      "explicit": false,
      "appleUrl": "https://music.apple.com/us/album/a-la-mala/6773419416?i=6773419417",
      "appleId": "6773419417"
    },
    {
      "position": 40,
      "title": "Destiny",
      "artistNames": [
        "Thaiboy Digital & swedm®"
      ],
      "artists": [
        {
          "name": "Thaiboy Digital & swedm®",
          "appleUrl": null
        }
      ],
      "album": {
        "name": "Paradise",
        "releaseDate": null,
        "coverImage": "https://is1-ssl.mzstatic.com/image/thumb/Music221/v4/e1/f3/49/e1f34952-74ac-d69e-f364-9859cee06c46/4426.jpg/600x600bb.jpg",
        "appleUrl": "https://music.apple.com/us/album/destiny/1887985073"
      },
      "durationMs": 161194,
      "explicit": false,
      "appleUrl": "https://music.apple.com/us/album/destiny/1887985073?i=1887985486",
      "appleId": "1887985486"
    },
    {
      "position": 41,
      "title": "Soleil (feat. Isabella Lovestory)",
      "artistNames": [
        "B0YG1RL & NOVAGANG"
      ],
      "artists": [
        {
          "name": "B0YG1RL & NOVAGANG",
          "appleUrl": null
        }
      ],
      "album": {
        "name": "EXIT 2B",
        "releaseDate": null,
        "coverImage": "https://is1-ssl.mzstatic.com/image/thumb/Music221/v4/7a/89/22/7a892272-1bfd-cdb7-7416-9f505260c96b/4520.jpg/600x600bb.jpg",
        "appleUrl": "https://music.apple.com/us/album/soleil-feat-isabella-lovestory/6769526101"
      },
      "durationMs": 131354,
      "explicit": false,
      "appleUrl": "https://music.apple.com/us/album/soleil-feat-isabella-lovestory/6769526101?i=6769526348",
      "appleId": "6769526348"
    },
    {
      "position": 42,
      "title": "i got a gun",
      "artistNames": [
        "Chanpan"
      ],
      "artists": [
        {
          "name": "Chanpan",
          "appleUrl": null
        }
      ],
      "album": {
        "name": "autogratis",
        "releaseDate": null,
        "coverImage": "https://is1-ssl.mzstatic.com/image/thumb/Music221/v4/ec/44/bc/ec44bc1b-1c4e-f73a-3f6d-1cd00d95f306/820200983541.jpg/600x600bb.jpg",
        "appleUrl": "https://music.apple.com/us/album/i-got-a-gun/1892181981"
      },
      "durationMs": 157160,
      "explicit": false,
      "appleUrl": "https://music.apple.com/us/album/i-got-a-gun/1892181981?i=1892182177",
      "appleId": "1892182177"
    },
    {
      "position": 43,
      "title": "Makeover",
      "artistNames": [
        "Hyd"
      ],
      "artists": [
        {
          "name": "Hyd",
          "appleUrl": null
        }
      ],
      "album": {
        "name": "Hold Onto Me Infinity",
        "releaseDate": null,
        "coverImage": "https://is1-ssl.mzstatic.com/image/thumb/Music211/v4/14/c1/16/14c11664-f3fa-5d6b-f102-9db79b70207d/63273.jpg/600x600bb.jpg",
        "appleUrl": "https://music.apple.com/us/album/makeover/1879596248"
      },
      "durationMs": 264768,
      "explicit": false,
      "appleUrl": "https://music.apple.com/us/album/makeover/1879596248?i=1879596492",
      "appleId": "1879596492"
    },
    {
      "position": 44,
      "title": "outta time",
      "artistNames": [
        "Kelela & A. K. Paul"
      ],
      "artists": [
        {
          "name": "Kelela & A. K. Paul",
          "appleUrl": null
        }
      ],
      "album": {
        "name": "new avatar",
        "releaseDate": null,
        "coverImage": "https://is1-ssl.mzstatic.com/image/thumb/Music211/v4/7a/a8/9e/7aa89e2c-ebb2-f4c4-fc20-42b17b465601/5056818808807.png/600x600bb.jpg",
        "appleUrl": "https://music.apple.com/us/album/outta-time/1888561538"
      },
      "durationMs": 251173,
      "explicit": true,
      "appleUrl": "https://music.apple.com/us/album/outta-time/1888561538?i=1888561544",
      "appleId": "1888561544"
    },
    {
      "position": 45,
      "title": "Bitches Talk Shit",
      "artistNames": [
        "Sophia Stel"
      ],
      "artists": [
        {
          "name": "Sophia Stel",
          "appleUrl": null
        }
      ],
      "album": {
        "name": "Bitches Talk Shit - Single",
        "releaseDate": null,
        "coverImage": "https://is1-ssl.mzstatic.com/image/thumb/Music211/v4/aa/de/2b/aade2b26-54bd-bb24-9749-35db4ac4b0f3/823375083795_Cover.jpg/600x600bb.jpg",
        "appleUrl": "https://music.apple.com/us/album/bitches-talk-shit/1888034538"
      },
      "durationMs": 219969,
      "explicit": true,
      "appleUrl": "https://music.apple.com/us/album/bitches-talk-shit/1888034538?i=1888034540",
      "appleId": "1888034540"
    },
    {
      "position": 46,
      "title": "encore, encore",
      "artistNames": [
        "venbee"
      ],
      "artists": [
        {
          "name": "venbee",
          "appleUrl": null
        }
      ],
      "album": {
        "name": "encore, encore - Single",
        "releaseDate": null,
        "coverImage": "https://is1-ssl.mzstatic.com/image/thumb/Music221/v4/94/1e/61/941e6171-9eb4-ee38-476a-c962b26e4bd1/3448166.jpg/600x600bb.jpg",
        "appleUrl": "https://music.apple.com/us/album/encore-encore/6769322039"
      },
      "durationMs": 129887,
      "explicit": true,
      "appleUrl": "https://music.apple.com/us/album/encore-encore/6769322039?i=6769322040",
      "appleId": "6769322040"
    },
    {
      "position": 47,
      "title": "TURBO",
      "artistNames": [
        "Andy Mineo, Wordsplayed & Magic & Bird"
      ],
      "artists": [
        {
          "name": "Andy Mineo, Wordsplayed & Magic & Bird",
          "appleUrl": null
        }
      ],
      "album": {
        "name": "FIRE FROM ABOVE - Single",
        "releaseDate": null,
        "coverImage": "https://is1-ssl.mzstatic.com/image/thumb/Music221/v4/13/cf/a3/13cfa31a-9cf4-d9c9-eacb-d2aa59ac0ffe/193436471862_MagicBirdContentCoversFFAcoverwtextures.jpg/600x600bb.jpg",
        "appleUrl": "https://music.apple.com/us/album/turbo/6768346522"
      },
      "durationMs": 203883,
      "explicit": false,
      "appleUrl": "https://music.apple.com/us/album/turbo/6768346522?i=6768346524",
      "appleId": "6768346524"
    },
    {
      "position": 48,
      "title": "Blondie",
      "artistNames": [
        "Bladee"
      ],
      "artists": [
        {
          "name": "Bladee",
          "appleUrl": null
        }
      ],
      "album": {
        "name": "Blondie - Single",
        "releaseDate": null,
        "coverImage": "https://is1-ssl.mzstatic.com/image/thumb/Music211/v4/69/13/f7/6913f76d-f000-9c0a-ad5f-7b32cef82701/820233303200.jpg/600x600bb.jpg",
        "appleUrl": "https://music.apple.com/us/album/blondie/6767655803"
      },
      "durationMs": 188853,
      "explicit": true,
      "appleUrl": "https://music.apple.com/us/album/blondie/6767655803?i=6767655804",
      "appleId": "6767655804"
    },
    {
      "position": 49,
      "title": "Together (feat. Nikki Nair, Jessy Lanza & Prentiss)",
      "artistNames": [
        "The Avalanches"
      ],
      "artists": [
        {
          "name": "The Avalanches",
          "appleUrl": null
        }
      ],
      "album": {
        "name": "Together (feat. Nikki Nair, Jessy Lanza & Prentiss) - Single",
        "releaseDate": null,
        "coverImage": "https://is1-ssl.mzstatic.com/image/thumb/Music211/v4/bf/6e/a4/bf6ea4c0-35d8-5ea8-5cca-042a6e7bc5a8/26UMGIM46326.rgb.jpg/600x600bb.jpg",
        "appleUrl": "https://music.apple.com/us/album/together-feat-nikki-nair-jessy-lanza-prentiss/1895215105"
      },
      "durationMs": 198667,
      "explicit": false,
      "appleUrl": "https://music.apple.com/us/album/together-feat-nikki-nair-jessy-lanza-prentiss/1895215105?i=6763207821",
      "appleId": "6763207821"
    },
    {
      "position": 50,
      "title": "8",
      "artistNames": [
        "benzii"
      ],
      "artists": [
        {
          "name": "benzii",
          "appleUrl": null
        }
      ],
      "album": {
        "name": "8 forever",
        "releaseDate": null,
        "coverImage": "https://is1-ssl.mzstatic.com/image/thumb/Music211/v4/75/a8/57/75a85761-6795-7577-f826-117aed97d17d/4448.jpg/600x600bb.jpg",
        "appleUrl": "https://music.apple.com/us/album/8/1891458014"
      },
      "durationMs": 126982,
      "explicit": false,
      "appleUrl": "https://music.apple.com/us/album/8/1891458014?i=1891458200",
      "appleId": "1891458200"
    },
    {
      "position": 51,
      "title": "Funny Friends",
      "artistNames": [
        "Thundercat & A$AP Rocky"
      ],
      "artists": [
        {
          "name": "Thundercat & A$AP Rocky",
          "appleUrl": null
        }
      ],
      "album": {
        "name": "Distracted",
        "releaseDate": null,
        "coverImage": "https://is1-ssl.mzstatic.com/image/thumb/Music221/v4/8a/9b/5f/8a9b5f98-1ba4-ea86-c70d-2bc19919e99d/5054429208733.png/600x600bb.jpg",
        "appleUrl": "https://music.apple.com/us/album/funny-friends/1861531667"
      },
      "durationMs": 155960,
      "explicit": true,
      "appleUrl": "https://music.apple.com/us/album/funny-friends/1861531667?i=1861531673",
      "appleId": "1861531673"
    },
    {
      "position": 52,
      "title": "androgynous",
      "artistNames": [
        "Rian Brazil"
      ],
      "artists": [
        {
          "name": "Rian Brazil",
          "appleUrl": null
        }
      ],
      "album": {
        "name": "engine heartbreak",
        "releaseDate": null,
        "coverImage": "https://is1-ssl.mzstatic.com/image/thumb/Music211/v4/e1/77/91/e17791dd-1229-970f-ffc6-a778eebe74f0/823375156918_Cover.jpg/600x600bb.jpg",
        "appleUrl": "https://music.apple.com/us/album/androgynous/1896041159"
      },
      "durationMs": 125849,
      "explicit": true,
      "appleUrl": "https://music.apple.com/us/album/androgynous/1896041159?i=6765698166",
      "appleId": "6765698166"
    },
    {
      "position": 53,
      "title": "Aset",
      "artistNames": [
        "Ibeyi"
      ],
      "artists": [
        {
          "name": "Ibeyi",
          "appleUrl": null
        }
      ],
      "album": {
        "name": "Offering",
        "releaseDate": null,
        "coverImage": "https://is1-ssl.mzstatic.com/image/thumb/Music221/v4/52/83/94/528394bc-6da8-6c5e-5b34-a2eba800e6bf/820233185707.jpg/600x600bb.jpg",
        "appleUrl": "https://music.apple.com/us/album/aset/1895972544"
      },
      "durationMs": 170093,
      "explicit": false,
      "appleUrl": "https://music.apple.com/us/album/aset/1895972544?i=6765497108",
      "appleId": "6765497108"
    },
    {
      "position": 54,
      "title": "Chalk",
      "artistNames": [
        "Antony Szmierek"
      ],
      "artists": [
        {
          "name": "Antony Szmierek",
          "appleUrl": null
        }
      ],
      "album": {
        "name": "Decoding Birdsong",
        "releaseDate": null,
        "coverImage": "https://is1-ssl.mzstatic.com/image/thumb/Music221/v4/5b/06/cd/5b06cd49-10b2-61ea-db25-eb55330cc688/9341004150065_Cover.jpg/600x600bb.jpg",
        "appleUrl": "https://music.apple.com/us/album/chalk/1891979477"
      },
      "durationMs": 322347,
      "explicit": false,
      "appleUrl": "https://music.apple.com/us/album/chalk/1891979477?i=1891979786",
      "appleId": "1891979786"
    },
    {
      "position": 55,
      "title": "Drive",
      "artistNames": [
        "Lucy Lamb"
      ],
      "artists": [
        {
          "name": "Lucy Lamb",
          "appleUrl": null
        }
      ],
      "album": {
        "name": "Lucy Lamb",
        "releaseDate": null,
        "coverImage": "https://is1-ssl.mzstatic.com/image/thumb/Music221/v4/c6/55/56/c65556e3-6f8b-ec64-46e6-0f36cf363c73/9332727137303_cover.jpg/600x600bb.jpg",
        "appleUrl": "https://music.apple.com/us/album/drive/1879924578"
      },
      "durationMs": 213861,
      "explicit": false,
      "appleUrl": "https://music.apple.com/us/album/drive/1879924578?i=1879925137",
      "appleId": "1879925137"
    },
    {
      "position": 56,
      "title": "Low End Skeeza",
      "artistNames": [
        "sha ray & DJ Haram"
      ],
      "artists": [
        {
          "name": "sha ray & DJ Haram",
          "appleUrl": null
        }
      ],
      "album": {
        "name": "Critical Thot",
        "releaseDate": null,
        "coverImage": "https://is1-ssl.mzstatic.com/image/thumb/Music211/v4/66/74/6a/66746a7a-ed65-a742-2d84-46607bdbcebf/5063916713742_cover.jpg/600x600bb.jpg",
        "appleUrl": "https://music.apple.com/us/album/low-end-skeeza/1885857747"
      },
      "durationMs": 163902,
      "explicit": false,
      "appleUrl": "https://music.apple.com/us/album/low-end-skeeza/1885857747?i=1885858452",
      "appleId": "1885858452"
    },
    {
      "position": 57,
      "title": "Klouds Will Carry Me To Sleep",
      "artistNames": [
        "Gelli Haha"
      ],
      "artists": [
        {
          "name": "Gelli Haha",
          "appleUrl": null
        }
      ],
      "album": {
        "name": "Switcheroo",
        "releaseDate": null,
        "coverImage": "https://is1-ssl.mzstatic.com/image/thumb/Music221/v4/a3/2e/0d/a32e0d5b-a1ba-1975-ae0f-93311692da46/124633.jpg/600x600bb.jpg",
        "appleUrl": "https://music.apple.com/us/album/klouds-will-carry-me-to-sleep/1882818124"
      },
      "durationMs": 224418,
      "explicit": false,
      "appleUrl": "https://music.apple.com/us/album/klouds-will-carry-me-to-sleep/1882818124?i=1882818391",
      "appleId": "1882818391"
    },
    {
      "position": 58,
      "title": "OLD TECHNOLOGY",
      "artistNames": [
        "Slayyyter"
      ],
      "artists": [
        {
          "name": "Slayyyter",
          "appleUrl": null
        }
      ],
      "album": {
        "name": "WOR$T GIRL IN AMERICA",
        "releaseDate": null,
        "coverImage": "https://is1-ssl.mzstatic.com/image/thumb/Music211/v4/e7/41/d8/e741d8f3-f8db-d401-5d93-fdfd69d8f17e/196873835891.jpg/600x600bb.jpg",
        "appleUrl": "https://music.apple.com/us/album/old-technology/1867530577"
      },
      "durationMs": 159198,
      "explicit": true,
      "appleUrl": "https://music.apple.com/us/album/old-technology/1867530577?i=1867531318",
      "appleId": "1867531318"
    },
    {
      "position": 59,
      "title": "What You Want (feat. Justice) [Fcukers Remix]",
      "artistNames": [
        "Angèle & Fcukers"
      ],
      "artists": [
        {
          "name": "Angèle & Fcukers",
          "appleUrl": null
        }
      ],
      "album": {
        "name": "What You Want (Fcukers Remix) [feat. Justice] - Single",
        "releaseDate": null,
        "coverImage": "https://is1-ssl.mzstatic.com/image/thumb/Music221/v4/e7/37/38/e73738d3-c0fe-aa48-6e43-03573f52818f/5056556181774_cover.jpg/600x600bb.jpg",
        "appleUrl": "https://music.apple.com/us/album/what-you-want-feat-justice-fcukers-remix/1896232934"
      },
      "durationMs": 202773,
      "explicit": false,
      "appleUrl": "https://music.apple.com/us/album/what-you-want-feat-justice-fcukers-remix/1896232934?i=6766197772",
      "appleId": "6766197772"
    },
    {
      "position": 60,
      "title": "Boys In Blue",
      "artistNames": [
        "Nia Archives"
      ],
      "artists": [
        {
          "name": "Nia Archives",
          "appleUrl": null
        }
      ],
      "album": {
        "name": "Emotional Junglist",
        "releaseDate": null,
        "coverImage": "https://is1-ssl.mzstatic.com/image/thumb/Music211/v4/cd/04/ea/cd04ea55-727d-782a-5ca6-265e0ecc1040/26UMGIM39397.rgb.jpg/600x600bb.jpg",
        "appleUrl": "https://music.apple.com/us/album/boys-in-blue/1892437345"
      },
      "durationMs": 153046,
      "explicit": false,
      "appleUrl": "https://music.apple.com/us/album/boys-in-blue/1892437345?i=1892437471",
      "appleId": "1892437471"
    },
    {
      "position": 61,
      "title": "Después de abandonar, ten fuerte el corazón",
      "artistNames": [
        "Planeta No"
      ],
      "artists": [
        {
          "name": "Planeta No",
          "appleUrl": null
        }
      ],
      "album": {
        "name": "Un Abrazo",
        "releaseDate": null,
        "coverImage": "https://is1-ssl.mzstatic.com/image/thumb/Music211/v4/04/e1/06/04e106cd-880a-a059-74be-32712308bbfd/824296307250_cover.jpg/600x600bb.jpg",
        "appleUrl": "https://music.apple.com/us/album/despu%C3%A9s-de-abandonar-ten-fuerte-el-coraz%C3%B3n/1893509883"
      },
      "durationMs": 185594,
      "explicit": false,
      "appleUrl": "https://music.apple.com/us/album/despu%C3%A9s-de-abandonar-ten-fuerte-el-coraz%C3%B3n/1893509883?i=1893509886",
      "appleId": "1893509886"
    },
    {
      "position": 62,
      "title": "The Way I Love",
      "artistNames": [
        "Faye Meana"
      ],
      "artists": [
        {
          "name": "Faye Meana",
          "appleUrl": null
        }
      ],
      "album": {
        "name": "The Way I Love - Single",
        "releaseDate": null,
        "coverImage": "https://is1-ssl.mzstatic.com/image/thumb/Music211/v4/ed/6e/38/ed6e3861-0268-f2c0-315f-e3c8e9763783/823375137870_Cover.jpg/600x600bb.jpg",
        "appleUrl": "https://music.apple.com/us/album/the-way-i-love/1895125948"
      },
      "durationMs": 186308,
      "explicit": false,
      "appleUrl": "https://music.apple.com/us/album/the-way-i-love/1895125948?i=6763025070",
      "appleId": "6763025070"
    },
    {
      "position": 63,
      "title": "Endlessly",
      "artistNames": [
        "Jump Source, Patrick Holland, Priori & BEA1991"
      ],
      "artists": [
        {
          "name": "Jump Source, Patrick Holland, Priori & BEA1991",
          "appleUrl": null
        }
      ],
      "album": {
        "name": "Fold",
        "releaseDate": null,
        "coverImage": "https://is1-ssl.mzstatic.com/image/thumb/Music221/v4/a9/74/d5/a974d5e2-d288-d8cc-8d19-1cc226cc4f00/4486.jpg/600x600bb.jpg",
        "appleUrl": "https://music.apple.com/us/album/endlessly/1876022817"
      },
      "durationMs": 357467,
      "explicit": false,
      "appleUrl": "https://music.apple.com/us/album/endlessly/1876022817?i=1876022833",
      "appleId": "1876022833"
    },
    {
      "position": 64,
      "title": "Lockup",
      "artistNames": [
        "Overmono"
      ],
      "artists": [
        {
          "name": "Overmono",
          "appleUrl": null
        }
      ],
      "album": {
        "name": "Pure Devotion",
        "releaseDate": null,
        "coverImage": "https://is1-ssl.mzstatic.com/image/thumb/Music211/v4/6a/cd/25/6acd2504-b1ef-8988-8fe0-240a5a25e0bc/191404166871.png/600x600bb.jpg",
        "appleUrl": "https://music.apple.com/us/album/lockup/1894298100"
      },
      "durationMs": 271836,
      "explicit": false,
      "appleUrl": "https://music.apple.com/us/album/lockup/1894298100?i=1894298102",
      "appleId": "1894298102"
    },
    {
      "position": 65,
      "title": "Overload",
      "artistNames": [
        "MADMADMAD"
      ],
      "artists": [
        {
          "name": "MADMADMAD",
          "appleUrl": null
        }
      ],
      "album": {
        "name": "Overload - Single",
        "releaseDate": null,
        "coverImage": "https://is1-ssl.mzstatic.com/image/thumb/Music211/v4/3c/1d/91/3c1d910b-d9fe-e4ae-4704-5b5b5afe7fdb/5053760151920_cover.jpg/600x600bb.jpg",
        "appleUrl": "https://music.apple.com/us/album/overload/1893042854"
      },
      "durationMs": 177479,
      "explicit": false,
      "appleUrl": "https://music.apple.com/us/album/overload/1893042854?i=6762128870",
      "appleId": "6762128870"
    },
    {
      "position": 66,
      "title": "car crash",
      "artistNames": [
        "jigitz & Charlotte Plank"
      ],
      "artists": [
        {
          "name": "jigitz & Charlotte Plank",
          "appleUrl": null
        }
      ],
      "album": {
        "name": "car crash - Single",
        "releaseDate": null,
        "coverImage": "https://is1-ssl.mzstatic.com/image/thumb/Music211/v4/01/94/d2/0194d2e7-5c55-4a61-a99e-039b865103ca/823375083771_Cover.jpg/600x600bb.jpg",
        "appleUrl": "https://music.apple.com/us/album/car-crash/1888339560"
      },
      "durationMs": 160627,
      "explicit": true,
      "appleUrl": "https://music.apple.com/us/album/car-crash/1888339560?i=1888339561",
      "appleId": "1888339561"
    },
    {
      "position": 67,
      "title": "Your Turn",
      "artistNames": [
        "Babe Dylan"
      ],
      "artists": [
        {
          "name": "Babe Dylan",
          "appleUrl": null
        }
      ],
      "album": {
        "name": "Your Turn - Single",
        "releaseDate": null,
        "coverImage": "https://is1-ssl.mzstatic.com/image/thumb/Music221/v4/0d/99/78/0d99789c-ca59-cafd-8e25-0d5bc1ac547a/3689c60b-85dd-4c81-9c27-f2d29c5527a9.jpg/600x600bb.jpg",
        "appleUrl": "https://music.apple.com/us/album/your-turn/1886239785"
      },
      "durationMs": 151200,
      "explicit": false,
      "appleUrl": "https://music.apple.com/us/album/your-turn/1886239785?i=1886239787",
      "appleId": "1886239787"
    },
    {
      "position": 68,
      "title": "Game On (feat. JT)",
      "artistNames": [
        "Little Simz"
      ],
      "artists": [
        {
          "name": "Little Simz",
          "appleUrl": null
        }
      ],
      "album": {
        "name": "Sugar Girl - EP",
        "releaseDate": null,
        "coverImage": "https://is1-ssl.mzstatic.com/image/thumb/Music221/v4/30/64/10/3064103f-d543-bbdf-1461-947ecc5a49db/820233138581.jpg/600x600bb.jpg",
        "appleUrl": "https://music.apple.com/us/album/game-on-feat-jt/1895242144"
      },
      "durationMs": 149776,
      "explicit": true,
      "appleUrl": "https://music.apple.com/us/album/game-on-feat-jt/1895242144?i=6763271985",
      "appleId": "6763271985"
    },
    {
      "position": 69,
      "title": "CAMINO",
      "artistNames": [
        "Reyna Tropical & Xiuhtezcatl"
      ],
      "artists": [
        {
          "name": "Reyna Tropical & Xiuhtezcatl",
          "appleUrl": null
        }
      ],
      "album": {
        "name": "CAMINO - Single",
        "releaseDate": null,
        "coverImage": "https://is1-ssl.mzstatic.com/image/thumb/Music211/v4/b0/0c/88/b00c88f8-210f-39d8-ba8a-1f336b50baee/64955.jpg/600x600bb.jpg",
        "appleUrl": "https://music.apple.com/us/album/camino/1885545499"
      },
      "durationMs": 184832,
      "explicit": false,
      "appleUrl": "https://music.apple.com/us/album/camino/1885545499?i=1885545770",
      "appleId": "1885545770"
    },
    {
      "position": 70,
      "title": "Without u (feat. babygh0st)",
      "artistNames": [
        "Yesterdayneverhappened"
      ],
      "artists": [
        {
          "name": "Yesterdayneverhappened",
          "appleUrl": null
        }
      ],
      "album": {
        "name": "search bar",
        "releaseDate": null,
        "coverImage": "https://is1-ssl.mzstatic.com/image/thumb/Music211/v4/ec/d7/53/ecd7533b-9eef-f96d-1f02-8160a99f4798/824296386095_cover.jpg/600x600bb.jpg",
        "appleUrl": "https://music.apple.com/us/album/without-u-feat-babygh0st/6770561119"
      },
      "durationMs": 123000,
      "explicit": false,
      "appleUrl": "https://music.apple.com/us/album/without-u-feat-babygh0st/6770561119?i=6770561120",
      "appleId": "6770561120"
    },
    {
      "position": 71,
      "title": "Read My Lips",
      "artistNames": [
        "Young Saab"
      ],
      "artists": [
        {
          "name": "Young Saab",
          "appleUrl": null
        }
      ],
      "album": {
        "name": "Read My Lips - Single",
        "releaseDate": null,
        "coverImage": "https://is1-ssl.mzstatic.com/image/thumb/Music221/v4/e6/5c/62/e65c621e-b3f0-d8a8-763c-edf7c3e63e69/5063960115509_cover.jpg/600x600bb.jpg",
        "appleUrl": "https://music.apple.com/us/album/read-my-lips/1889629507"
      },
      "durationMs": 120494,
      "explicit": false,
      "appleUrl": "https://music.apple.com/us/album/read-my-lips/1889629507?i=1889629511",
      "appleId": "1889629511"
    },
    {
      "position": 72,
      "title": "Weirdo Magnet",
      "artistNames": [
        "Disgusting Sisters"
      ],
      "artists": [
        {
          "name": "Disgusting Sisters",
          "appleUrl": null
        }
      ],
      "album": {
        "name": "Weirdo Magnet - Single",
        "releaseDate": null,
        "coverImage": "https://is1-ssl.mzstatic.com/image/thumb/Music221/v4/1a/c5/c4/1ac5c420-b7d8-75f0-59af-325489d7028e/5400863193256_cover.jpg/600x600bb.jpg",
        "appleUrl": "https://music.apple.com/us/album/weirdo-magnet/1886123887"
      },
      "durationMs": 167083,
      "explicit": false,
      "appleUrl": "https://music.apple.com/us/album/weirdo-magnet/1886123887?i=1886123890",
      "appleId": "1886123890"
    },
    {
      "position": 73,
      "title": "Must Be",
      "artistNames": [
        "Tkay Maidza"
      ],
      "artists": [
        {
          "name": "Tkay Maidza",
          "appleUrl": null
        }
      ],
      "album": {
        "name": "Must Be - Single",
        "releaseDate": null,
        "coverImage": "https://is1-ssl.mzstatic.com/image/thumb/Music211/v4/c6/5f/bd/c65fbd60-e77c-d44a-f07d-5a5c7270f94b/DSCF8306-copy-1766de55.png/600x600bb.jpg",
        "appleUrl": "https://music.apple.com/us/album/must-be/1858663212"
      },
      "durationMs": 175040,
      "explicit": true,
      "appleUrl": "https://music.apple.com/us/album/must-be/1858663212?i=1858663213",
      "appleId": "1858663213"
    },
    {
      "position": 74,
      "title": "PAN Night",
      "artistNames": [
        "Callahan & Witscher"
      ],
      "artists": [
        {
          "name": "Callahan & Witscher",
          "appleUrl": null
        }
      ],
      "album": {
        "name": "Sorry To Hear That",
        "releaseDate": null,
        "coverImage": "https://is1-ssl.mzstatic.com/image/thumb/Music211/v4/8b/f1/86/8bf18648-024c-c6ba-964b-94023cb8419b/63319.jpg/600x600bb.jpg",
        "appleUrl": "https://music.apple.com/us/album/pan-night/1879864827"
      },
      "durationMs": 196519,
      "explicit": false,
      "appleUrl": "https://music.apple.com/us/album/pan-night/1879864827?i=1879865172",
      "appleId": "1879865172"
    },
    {
      "position": 75,
      "title": "Hurry, Grin",
      "artistNames": [
        "Lecx Stacy"
      ],
      "artists": [
        {
          "name": "Lecx Stacy",
          "appleUrl": null
        }
      ],
      "album": {
        "name": "Hurry, Grin - Single",
        "releaseDate": null,
        "coverImage": "https://is1-ssl.mzstatic.com/image/thumb/Music211/v4/00/22/52/0022529d-35e0-cff0-83ef-3df58876fa82/632665345617_Cover.jpg/600x600bb.jpg",
        "appleUrl": "https://music.apple.com/us/album/hurry-grin/1884292833"
      },
      "durationMs": 213353,
      "explicit": false,
      "appleUrl": "https://music.apple.com/us/album/hurry-grin/1884292833?i=1884292835",
      "appleId": "1884292835"
    },
    {
      "position": 76,
      "title": "if you wanna party, come over to my house",
      "artistNames": [
        "Fcukers"
      ],
      "artists": [
        {
          "name": "Fcukers",
          "appleUrl": null
        }
      ],
      "album": {
        "name": "Ö",
        "releaseDate": null,
        "coverImage": "https://is1-ssl.mzstatic.com/image/thumb/Music221/v4/87/b3/85/87b38597-7032-1783-bcd6-7e77af31df9a/5054429208382.png/600x600bb.jpg",
        "appleUrl": "https://music.apple.com/us/album/if-you-wanna-party-come-over-to-my-house/1861895134"
      },
      "durationMs": 171613,
      "explicit": false,
      "appleUrl": "https://music.apple.com/us/album/if-you-wanna-party-come-over-to-my-house/1861895134?i=1861895281",
      "appleId": "1861895281"
    },
    {
      "position": 77,
      "title": "iPod Touch",
      "artistNames": [
        "Ninajirachi"
      ],
      "artists": [
        {
          "name": "Ninajirachi",
          "appleUrl": null
        }
      ],
      "album": {
        "name": "I Love My Computer",
        "releaseDate": null,
        "coverImage": "https://is1-ssl.mzstatic.com/image/thumb/Music211/v4/51/41/9c/51419c3f-dce3-5072-eb94-fc453f6fdb87/199350974793.jpg/600x600bb.jpg",
        "appleUrl": "https://music.apple.com/us/album/ipod-touch/1824602984"
      },
      "durationMs": 196522,
      "explicit": false,
      "appleUrl": "https://music.apple.com/us/album/ipod-touch/1824602984?i=1824602986",
      "appleId": "1824602986"
    },
    {
      "position": 78,
      "title": "Fail-safe",
      "artistNames": [
        "DJ_Dave"
      ],
      "artists": [
        {
          "name": "DJ_Dave",
          "appleUrl": null
        }
      ],
      "album": {
        "name": "Fail-safe - Single",
        "releaseDate": null,
        "coverImage": "https://is1-ssl.mzstatic.com/image/thumb/Music221/v4/d1/40/79/d1407980-d56b-5344-4404-1121d11c9503/4490.jpg/600x600bb.jpg",
        "appleUrl": "https://music.apple.com/us/album/fail-safe/1893808624"
      },
      "durationMs": 207435,
      "explicit": false,
      "appleUrl": "https://music.apple.com/us/album/fail-safe/1893808624?i=1893808625",
      "appleId": "1893808625"
    },
    {
      "position": 79,
      "title": "Borealis",
      "artistNames": [
        "J Scienide"
      ],
      "artists": [
        {
          "name": "J Scienide",
          "appleUrl": null
        }
      ],
      "album": {
        "name": "Borealis - Single",
        "releaseDate": null,
        "coverImage": "https://is1-ssl.mzstatic.com/image/thumb/Music211/v4/fa/16/27/fa1627b8-f8e6-1360-6e0e-8e7f9d850f42/5053760150350_cover.jpg/600x600bb.jpg",
        "appleUrl": "https://music.apple.com/us/album/borealis/1885584703"
      },
      "durationMs": 191933,
      "explicit": false,
      "appleUrl": "https://music.apple.com/us/album/borealis/1885584703?i=1885584918",
      "appleId": "1885584918"
    },
    {
      "position": 80,
      "title": "Shame4ever",
      "artistNames": [
        "Helena DLX"
      ],
      "artists": [
        {
          "name": "Helena DLX",
          "appleUrl": null
        }
      ],
      "album": {
        "name": "Kiss World Online - Single",
        "releaseDate": null,
        "coverImage": "https://is1-ssl.mzstatic.com/image/thumb/Music211/v4/19/3f/92/193f92ed-e9a9-852a-61b1-8ce3f4125265/4352.jpg/600x600bb.jpg",
        "appleUrl": "https://music.apple.com/us/album/shame4ever/1882128857"
      },
      "durationMs": 208024,
      "explicit": false,
      "appleUrl": "https://music.apple.com/us/album/shame4ever/1882128857?i=1882128861",
      "appleId": "1882128861"
    },
    {
      "position": 81,
      "title": "Smile",
      "artistNames": [
        "Two Shell"
      ],
      "artists": [
        {
          "name": "Two Shell",
          "appleUrl": null
        }
      ],
      "album": {
        "name": "Smile - Single",
        "releaseDate": null,
        "coverImage": "https://is1-ssl.mzstatic.com/image/thumb/Music211/v4/50/e3/f8/50e3f8f5-7401-7e22-619a-cedf1e215e18/889030048974.png/600x600bb.jpg",
        "appleUrl": "https://music.apple.com/us/album/smile/1882074557"
      },
      "durationMs": 227881,
      "explicit": false,
      "appleUrl": "https://music.apple.com/us/album/smile/1882074557?i=1882074559",
      "appleId": "1882074559"
    },
    {
      "position": 82,
      "title": "2SIDED",
      "artistNames": [
        "Arlo Parks"
      ],
      "artists": [
        {
          "name": "Arlo Parks",
          "appleUrl": null
        }
      ],
      "album": {
        "name": "Ambiguous Desire",
        "releaseDate": null,
        "coverImage": "https://is1-ssl.mzstatic.com/image/thumb/Music211/v4/86/10/2a/86102a67-2d84-24f7-dd60-4c7a6846ed05/5400863205140_cover.jpg/600x600bb.jpg",
        "appleUrl": "https://music.apple.com/us/album/2sided/1862570378"
      },
      "durationMs": 177473,
      "explicit": false,
      "appleUrl": "https://music.apple.com/us/album/2sided/1862570378?i=1862571197",
      "appleId": "1862571197"
    },
    {
      "position": 83,
      "title": "I Do, I Do",
      "artistNames": [
        "Dua Saleh"
      ],
      "artists": [
        {
          "name": "Dua Saleh",
          "appleUrl": null
        }
      ],
      "album": {
        "name": "Of Earth & Wires",
        "releaseDate": null,
        "coverImage": "https://is1-ssl.mzstatic.com/image/thumb/Music211/v4/10/7f/8e/107f8e00-bf5c-30a0-4666-37a02b2826a6/61520.jpg/600x600bb.jpg",
        "appleUrl": "https://music.apple.com/us/album/i-do-i-do/1868826829"
      },
      "durationMs": 135893,
      "explicit": false,
      "appleUrl": "https://music.apple.com/us/album/i-do-i-do/1868826829?i=1868827006",
      "appleId": "1868827006"
    },
    {
      "position": 84,
      "title": "You Say I Love You",
      "artistNames": [
        "Quiet Light"
      ],
      "artists": [
        {
          "name": "Quiet Light",
          "appleUrl": null
        }
      ],
      "album": {
        "name": "Blue Angel Sparkling Silver 2",
        "releaseDate": null,
        "coverImage": "https://is1-ssl.mzstatic.com/image/thumb/Music221/v4/26/92/8a/26928a3a-030e-3f28-ed77-c67bb9c08105/198704947742_Cover.jpg/600x600bb.jpg",
        "appleUrl": "https://music.apple.com/us/album/you-say-i-love-you/1868660166"
      },
      "durationMs": 186446,
      "explicit": false,
      "appleUrl": "https://music.apple.com/us/album/you-say-i-love-you/1868660166?i=1868660549",
      "appleId": "1868660549"
    },
    {
      "position": 85,
      "title": "MILLENIAL CHILD",
      "artistNames": [
        "Sean Leon & God's ALGORITHM"
      ],
      "artists": [
        {
          "name": "Sean Leon & God's ALGORITHM",
          "appleUrl": null
        }
      ],
      "album": {
        "name": "MILLENIAL CHILD - Single",
        "releaseDate": null,
        "coverImage": "https://is1-ssl.mzstatic.com/image/thumb/Music221/v4/36/37/ba/3637ba0d-a8fe-d0d6-7667-b1576695c415/663918951187.jpg/600x600bb.jpg",
        "appleUrl": "https://music.apple.com/us/album/millenial-child/1890325361"
      },
      "durationMs": 129697,
      "explicit": false,
      "appleUrl": "https://music.apple.com/us/album/millenial-child/1890325361?i=1890325362",
      "appleId": "1890325362"
    },
    {
      "position": 86,
      "title": "Get A Grip (Radio Edit)",
      "artistNames": [
        "Fundido & Emma Dufaux"
      ],
      "artists": [
        {
          "name": "Fundido & Emma Dufaux",
          "appleUrl": null
        }
      ],
      "album": {
        "name": "Get A Grip - Single",
        "releaseDate": null,
        "coverImage": "https://is1-ssl.mzstatic.com/image/thumb/Music221/v4/fa/0d/be/fa0dbe4a-f8df-67c0-73b3-002f4a4bf221/63832.jpg/600x600bb.jpg",
        "appleUrl": "https://music.apple.com/us/album/get-a-grip-radio-edit/1884125925"
      },
      "durationMs": 240400,
      "explicit": false,
      "appleUrl": "https://music.apple.com/us/album/get-a-grip-radio-edit/1884125925?i=1884125926",
      "appleId": "1884125926"
    },
    {
      "position": 87,
      "title": "Play (Objekt Remix)",
      "artistNames": [
        "james K"
      ],
      "artists": [
        {
          "name": "james K",
          "appleUrl": null
        }
      ],
      "album": {
        "name": "Friend Remixes",
        "releaseDate": null,
        "coverImage": "https://is1-ssl.mzstatic.com/image/thumb/Music221/v4/ee/7c/fd/ee7cfd43-d1f2-11c9-2c68-40b96c0a92e5/191400680906.png/600x600bb.jpg",
        "appleUrl": "https://music.apple.com/us/album/play-objekt-remix/1895294388"
      },
      "durationMs": 237600,
      "explicit": false,
      "appleUrl": "https://music.apple.com/us/album/play-objekt-remix/1895294388?i=6763395297",
      "appleId": "6763395297"
    },
    {
      "position": 88,
      "title": "Where's Your Head At (Steve Angello Remix)",
      "artistNames": [
        "Basement Jaxx"
      ],
      "artists": [
        {
          "name": "Basement Jaxx",
          "appleUrl": null
        }
      ],
      "album": {
        "name": "Where's Your Head At (Steve Angello Remix) - Single",
        "releaseDate": null,
        "coverImage": "https://is1-ssl.mzstatic.com/image/thumb/Music211/v4/cc/98/fc/cc98fc6c-dce3-9d0f-6a35-f98f90dedc1d/191404164860.png/600x600bb.jpg",
        "appleUrl": "https://music.apple.com/us/album/wheres-your-head-at-steve-angello-remix/1881942002"
      },
      "durationMs": 180025,
      "explicit": false,
      "appleUrl": "https://music.apple.com/us/album/wheres-your-head-at-steve-angello-remix/1881942002?i=1881942121",
      "appleId": "1881942121"
    },
    {
      "position": 89,
      "title": "be the girl!",
      "artistNames": [
        "hemlocke springs"
      ],
      "artists": [
        {
          "name": "hemlocke springs",
          "appleUrl": null
        }
      ],
      "album": {
        "name": "the apple tree under the sea",
        "releaseDate": null,
        "coverImage": "https://is1-ssl.mzstatic.com/image/thumb/Music221/v4/2e/d3/a1/2ed3a1ee-c107-fee3-bdf4-9658123b89c1/820200254528.jpg/600x600bb.jpg",
        "appleUrl": "https://music.apple.com/us/album/be-the-girl/1877161526"
      },
      "durationMs": 333956,
      "explicit": false,
      "appleUrl": "https://music.apple.com/us/album/be-the-girl/1877161526?i=1877161731",
      "appleId": "1877161731"
    },
    {
      "position": 90,
      "title": "Wait For You",
      "artistNames": [
        "WizTheMc"
      ],
      "artists": [
        {
          "name": "WizTheMc",
          "appleUrl": null
        }
      ],
      "album": {
        "name": "Wait For You - Single",
        "releaseDate": null,
        "coverImage": "https://is1-ssl.mzstatic.com/image/thumb/Music221/v4/12/07/c0/1207c047-6046-240c-c3a8-1641c39d3f7d/2643045.jpg/600x600bb.jpg",
        "appleUrl": "https://music.apple.com/us/album/wait-for-you/1890150375"
      },
      "durationMs": 169207,
      "explicit": false,
      "appleUrl": "https://music.apple.com/us/album/wait-for-you/1890150375?i=1890150533",
      "appleId": "1890150533"
    },
    {
      "position": 91,
      "title": "Lie2Me",
      "artistNames": [
        "DC THE DON"
      ],
      "artists": [
        {
          "name": "DC THE DON",
          "appleUrl": null
        }
      ],
      "album": {
        "name": "Lie2Me - Single",
        "releaseDate": null,
        "coverImage": "https://is1-ssl.mzstatic.com/image/thumb/Music211/v4/f7/93/12/f79312c3-fc37-423e-889e-4a9365172889/25UM2IM08122.rgb.jpg/600x600bb.jpg",
        "appleUrl": "https://music.apple.com/us/album/lie2me/1862762674"
      },
      "durationMs": 183421,
      "explicit": true,
      "appleUrl": "https://music.apple.com/us/album/lie2me/1862762674?i=1862762675",
      "appleId": "1862762675"
    },
    {
      "position": 92,
      "title": "Two Hearts",
      "artistNames": [
        "Danny L Harle & Dua Lipa"
      ],
      "artists": [
        {
          "name": "Danny L Harle & Dua Lipa",
          "appleUrl": null
        }
      ],
      "album": {
        "name": "Cerulean",
        "releaseDate": null,
        "coverImage": "https://is1-ssl.mzstatic.com/image/thumb/Music211/v4/a8/a6/a4/a8a6a497-12de-7f01-c3b9-9074ee2ef551/191404158579.png/600x600bb.jpg",
        "appleUrl": "https://music.apple.com/us/album/two-hearts/1847662970"
      },
      "durationMs": 232796,
      "explicit": false,
      "appleUrl": "https://music.apple.com/us/album/two-hearts/1847662970?i=1847663423",
      "appleId": "1847663423"
    },
    {
      "position": 93,
      "title": "The Troubles",
      "artistNames": [
        "glaive & kurtains"
      ],
      "artists": [
        {
          "name": "glaive & kurtains",
          "appleUrl": null
        }
      ],
      "album": {
        "name": "The Troubles - Single",
        "releaseDate": null,
        "coverImage": "https://is1-ssl.mzstatic.com/image/thumb/Music211/v4/27/ad/89/27ad891c-53e5-7cd6-316e-8bd17124cf20/663918959442.jpg/600x600bb.jpg",
        "appleUrl": "https://music.apple.com/us/album/the-troubles/1891514475"
      },
      "durationMs": 116620,
      "explicit": true,
      "appleUrl": "https://music.apple.com/us/album/the-troubles/1891514475?i=1891514476",
      "appleId": "1891514476"
    },
    {
      "position": 94,
      "title": "Toerags",
      "artistNames": [
        "teethin"
      ],
      "artists": [
        {
          "name": "teethin",
          "appleUrl": null
        }
      ],
      "album": {
        "name": "Toerags - Single",
        "releaseDate": null,
        "coverImage": "https://is1-ssl.mzstatic.com/image/thumb/Music221/v4/64/59/92/64599299-c9d1-d66b-e89c-21df969fcb01/8721465769555.png/600x600bb.jpg",
        "appleUrl": "https://music.apple.com/us/album/toerags/1876577285"
      },
      "durationMs": 147229,
      "explicit": true,
      "appleUrl": "https://music.apple.com/us/album/toerags/1876577285?i=1876577291",
      "appleId": "1876577291"
    },
    {
      "position": 95,
      "title": "Pick up the Check",
      "artistNames": [
        "BODEGA"
      ],
      "artists": [
        {
          "name": "BODEGA",
          "appleUrl": null
        }
      ],
      "album": {
        "name": "Pick up the Check - Single",
        "releaseDate": null,
        "coverImage": "https://is1-ssl.mzstatic.com/image/thumb/Music221/v4/23/2e/04/232e0470-050e-4cf3-b2d4-94b792d8e2ed/0840401724538.png/600x600bb.jpg",
        "appleUrl": "https://music.apple.com/us/album/pick-up-the-check/1887305450"
      },
      "durationMs": 278849,
      "explicit": false,
      "appleUrl": "https://music.apple.com/us/album/pick-up-the-check/1887305450?i=1887305451",
      "appleId": "1887305451"
    },
    {
      "position": 96,
      "title": "PUT THE FRIES IN THE BAG.",
      "artistNames": [
        "NESYA"
      ],
      "artists": [
        {
          "name": "NESYA",
          "appleUrl": null
        }
      ],
      "album": {
        "name": "PUT THE FRIES IN THE BAG. - Single",
        "releaseDate": null,
        "coverImage": "https://is1-ssl.mzstatic.com/image/thumb/Music211/v4/04/9f/e9/049fe9cd-42bd-d374-a334-02d73c73894f/823375094074_Cover.jpg/600x600bb.jpg",
        "appleUrl": "https://music.apple.com/us/album/put-the-fries-in-the-bag/1889838164"
      },
      "durationMs": 257044,
      "explicit": true,
      "appleUrl": "https://music.apple.com/us/album/put-the-fries-in-the-bag/1889838164?i=1889838168",
      "appleId": "1889838168"
    },
    {
      "position": 97,
      "title": "Take Off Late",
      "artistNames": [
        "15 15"
      ],
      "artists": [
        {
          "name": "15 15",
          "appleUrl": null
        }
      ],
      "album": {
        "name": "Mārara",
        "releaseDate": null,
        "coverImage": "https://is1-ssl.mzstatic.com/image/thumb/Music211/v4/43/5d/85/435d8509-0af4-b5c5-473e-eb514b1fd97e/191404654576.png/600x600bb.jpg",
        "appleUrl": "https://music.apple.com/us/album/take-off-late/1858554036"
      },
      "durationMs": 203733,
      "explicit": false,
      "appleUrl": "https://music.apple.com/us/album/take-off-late/1858554036?i=1858554342",
      "appleId": "1858554342"
    },
    {
      "position": 98,
      "title": "Lose Control",
      "artistNames": [
        "Ouri & umru"
      ],
      "artists": [
        {
          "name": "Ouri & umru",
          "appleUrl": null
        }
      ],
      "album": {
        "name": "Lose Control - Single",
        "releaseDate": null,
        "coverImage": "https://is1-ssl.mzstatic.com/image/thumb/Music211/v4/3f/e3/e3/3fe3e322-610d-6e85-2c96-3512f6e01840/820200367792.jpg/600x600bb.jpg",
        "appleUrl": "https://music.apple.com/us/album/lose-control/1878146560"
      },
      "durationMs": 191628,
      "explicit": false,
      "appleUrl": "https://music.apple.com/us/album/lose-control/1878146560?i=1878146562",
      "appleId": "1878146562"
    },
    {
      "position": 99,
      "title": "The Moon Cave (feat. Asha Puthli, Bobby Womack, David Jolicoeur, Jalen Ngonda & Black Thought)",
      "artistNames": [
        "Gorillaz"
      ],
      "artists": [
        {
          "name": "Gorillaz",
          "appleUrl": null
        }
      ],
      "album": {
        "name": "The Mountain",
        "releaseDate": null,
        "coverImage": "https://is1-ssl.mzstatic.com/image/thumb/Music221/v4/86/b5/3f/86b53fc7-cc73-c735-17fb-549fc459edca/199538459005.jpg/600x600bb.jpg",
        "appleUrl": "https://music.apple.com/us/album/the-moon-cave-feat-asha-puthli-bobby-womack-david/1837237742"
      },
      "durationMs": 297788,
      "explicit": false,
      "appleUrl": "https://music.apple.com/us/album/the-moon-cave-feat-asha-puthli-bobby-womack-david/1837237742?i=1837237761",
      "appleId": "1837237761"
    },
    {
      "position": 100,
      "title": "Zines & Gibberish",
      "artistNames": [
        "Ms* Gloom"
      ],
      "artists": [
        {
          "name": "Ms* Gloom",
          "appleUrl": null
        }
      ],
      "album": {
        "name": "J is for Joon",
        "releaseDate": null,
        "coverImage": "https://is1-ssl.mzstatic.com/image/thumb/Music221/v4/c2/f6/60/c2f6609f-72e2-fc23-4067-792538ef2edd/4256.jpg/600x600bb.jpg",
        "appleUrl": "https://music.apple.com/us/album/zines-gibberish/1870688244"
      },
      "durationMs": 234875,
      "explicit": false,
      "appleUrl": "https://music.apple.com/us/album/zines-gibberish/1870688244?i=1870689270",
      "appleId": "1870689270"
    }
  ]
}
